{
"meta":{"test_sets":[],"test_metrics":[],"learn_metrics":[{"best_value":"Min","name":"RMSE"}],"launch_mode":"Train","parameters":"","iteration_count":1000,"learn_sets":["learn"],"name":"experiment"},
"iterations":[
{"learn":[532195.0511],"iteration":0,"passed_time":0.002161311351,"remaining_time":2.159150039},
{"learn":[522688.7931],"iteration":1,"passed_time":0.003624977483,"remaining_time":1.808863764},
{"learn":[511998.5156],"iteration":2,"passed_time":0.004729026967,"remaining_time":1.571613295},
{"learn":[503582.6416],"iteration":3,"passed_time":0.006011667238,"remaining_time":1.496905142},
{"learn":[496359.3746],"iteration":4,"passed_time":0.007293756242,"remaining_time":1.451457492},
{"learn":[487543.6235],"iteration":5,"passed_time":0.008430521504,"remaining_time":1.396656396},
{"learn":[482624.4734],"iteration":6,"passed_time":0.009557286659,"remaining_time":1.355769379},
{"learn":[474657.6818],"iteration":7,"passed_time":0.01066957167,"remaining_time":1.323026887},
{"learn":[469941.163],"iteration":8,"passed_time":0.01168490709,"remaining_time":1.286638103},
{"learn":[462158.6943],"iteration":9,"passed_time":0.01296393247,"remaining_time":1.283429315},
{"learn":[458326.7683],"iteration":10,"passed_time":0.01411680425,"remaining_time":1.269229037},
{"learn":[454032.178],"iteration":11,"passed_time":0.01513979387,"remaining_time":1.246509695},
{"learn":[445835.2958],"iteration":12,"passed_time":0.01621104792,"remaining_time":1.230792638},
{"learn":[441052.0422],"iteration":13,"passed_time":0.01737166752,"remaining_time":1.223461727},
{"learn":[434843.3887],"iteration":14,"passed_time":0.01853109438,"remaining_time":1.216875198},
{"learn":[431074.9318],"iteration":15,"passed_time":0.0198054688,"remaining_time":1.218036331},
{"learn":[427320.971],"iteration":16,"passed_time":0.02088462788,"remaining_time":1.207622894},
{"learn":[423429.6458],"iteration":17,"passed_time":0.02212600613,"remaining_time":1.207096557},
{"learn":[418894.4053],"iteration":18,"passed_time":0.02327738501,"remaining_time":1.201848142},
{"learn":[412035.615],"iteration":19,"passed_time":0.02432063464,"remaining_time":1.191711098},
{"learn":[406309.4659],"iteration":20,"passed_time":0.02598000092,"remaining_time":1.2111629},
{"learn":[402892.2919],"iteration":21,"passed_time":0.02709502565,"remaining_time":1.204497049},
{"learn":[399765.8889],"iteration":22,"passed_time":0.02863604549,"remaining_time":1.216409411},
{"learn":[393766.2644],"iteration":23,"passed_time":0.0298714872,"remaining_time":1.214773813},
{"learn":[390795.518],"iteration":24,"passed_time":0.0314845976,"remaining_time":1.227899307},
{"learn":[387210.6397],"iteration":25,"passed_time":0.03290461861,"remaining_time":1.232657636},
{"learn":[383804.8903],"iteration":26,"passed_time":0.03445933997,"remaining_time":1.241812511},
{"learn":[380043.6506],"iteration":27,"passed_time":0.03548088468,"remaining_time":1.231693568},
{"learn":[375134.6588],"iteration":28,"passed_time":0.0365831498,"remaining_time":1.224904774},
{"learn":[371485.7004],"iteration":29,"passed_time":0.03750661391,"remaining_time":1.21271385},
{"learn":[367807.0741],"iteration":30,"passed_time":0.03852450522,"remaining_time":1.20420147},
{"learn":[364251.5312],"iteration":31,"passed_time":0.03947957202,"remaining_time":1.194257054},
{"learn":[360909.5066],"iteration":32,"passed_time":0.04048524575,"remaining_time":1.186340383},
{"learn":[356706.1119],"iteration":33,"passed_time":0.04143893887,"remaining_time":1.177353381},
{"learn":[352151.6118],"iteration":34,"passed_time":0.04237132349,"remaining_time":1.168237919},
{"learn":[349612.6784],"iteration":35,"passed_time":0.04329880184,"remaining_time":1.159445694},
{"learn":[346946.5905],"iteration":36,"passed_time":0.04427794402,"remaining_time":1.152423246},
{"learn":[341984.8521],"iteration":37,"passed_time":0.04537205617,"remaining_time":1.148629422},
{"learn":[338486.5895],"iteration":38,"passed_time":0.04636243868,"remaining_time":1.14241804},
{"learn":[336056.4596],"iteration":39,"passed_time":0.04734384607,"remaining_time":1.136252306},
{"learn":[332222.5658],"iteration":40,"passed_time":0.04826752066,"remaining_time":1.128989081},
{"learn":[329473.3612],"iteration":41,"passed_time":0.04926539593,"remaining_time":1.123720221},
{"learn":[327766.544],"iteration":42,"passed_time":0.0504463924,"remaining_time":1.122725524},
{"learn":[325282.8973],"iteration":43,"passed_time":0.05151151735,"remaining_time":1.119204786},
{"learn":[321078.853],"iteration":44,"passed_time":0.05251601285,"remaining_time":1.114506495},
{"learn":[318003.2674],"iteration":45,"passed_time":0.05347897333,"remaining_time":1.109107403},
{"learn":[314767.0639],"iteration":46,"passed_time":0.05455446371,"remaining_time":1.106178807},
{"learn":[312832.0693],"iteration":47,"passed_time":0.05566577278,"remaining_time":1.104037827},
{"learn":[310505.1458],"iteration":48,"passed_time":0.05678963495,"remaining_time":1.102182507},
{"learn":[308661.1138],"iteration":49,"passed_time":0.05780185611,"remaining_time":1.098235266},
{"learn":[306837.5206],"iteration":50,"passed_time":0.05891069661,"remaining_time":1.096201002},
{"learn":[305612.4149],"iteration":51,"passed_time":0.05983252696,"remaining_time":1.090792992},
{"learn":[303430.4961],"iteration":52,"passed_time":0.06099400354,"remaining_time":1.089836252},
{"learn":[301644.9506],"iteration":53,"passed_time":0.06198178559,"remaining_time":1.085829059},
{"learn":[300483.772],"iteration":54,"passed_time":0.06319380342,"remaining_time":1.085784441},
{"learn":[298374.4076],"iteration":55,"passed_time":0.06435339065,"remaining_time":1.0848143},
{"learn":[296147.7809],"iteration":56,"passed_time":0.06547349918,"remaining_time":1.083184381},
{"learn":[294254.9052],"iteration":57,"passed_time":0.06656533056,"remaining_time":1.081112783},
{"learn":[291198.7486],"iteration":58,"passed_time":0.06757226667,"remaining_time":1.077720389},
{"learn":[290348.2523],"iteration":59,"passed_time":0.06865484677,"remaining_time":1.075592599},
{"learn":[288868.4313],"iteration":60,"passed_time":0.0696136556,"remaining_time":1.071593813},
{"learn":[287525.0041],"iteration":61,"passed_time":0.07063244872,"remaining_time":1.068600595},
{"learn":[286526.8489],"iteration":62,"passed_time":0.07161942576,"remaining_time":1.065196856},
{"learn":[285525.2023],"iteration":63,"passed_time":0.07253508508,"remaining_time":1.060825619},
{"learn":[282448.5299],"iteration":64,"passed_time":0.07360712066,"remaining_time":1.05881012},
{"learn":[280005.4167],"iteration":65,"passed_time":0.07462425523,"remaining_time":1.056046279},
{"learn":[277478.7638],"iteration":66,"passed_time":0.07552841493,"remaining_time":1.05176136},
{"learn":[275007.507],"iteration":67,"passed_time":0.07645524679,"remaining_time":1.047886618},
{"learn":[273723.3374],"iteration":68,"passed_time":0.07741658011,"remaining_time":1.044562842},
{"learn":[272261.3256],"iteration":69,"passed_time":0.07835667564,"remaining_time":1.041024405},
{"learn":[269662.1079],"iteration":70,"passed_time":0.0792856424,"remaining_time":1.037413546},
{"learn":[268488.8229],"iteration":71,"passed_time":0.08017980912,"remaining_time":1.033428651},
{"learn":[266235.4723],"iteration":72,"passed_time":0.08112057303,"remaining_time":1.030120153},
{"learn":[264552.1892],"iteration":73,"passed_time":0.08214363307,"remaining_time":1.027905462},
{"learn":[262635.728],"iteration":74,"passed_time":0.08309498131,"remaining_time":1.024838103},
{"learn":[260625.0356],"iteration":75,"passed_time":0.08404229027,"remaining_time":1.021777319},
{"learn":[259118.2334],"iteration":76,"passed_time":0.08495243717,"remaining_time":1.018325968},
{"learn":[257498.7183],"iteration":77,"passed_time":0.08582411216,"remaining_time":1.014485018},
{"learn":[255045.991],"iteration":78,"passed_time":0.086707464,"remaining_time":1.010855371},
{"learn":[253707.1006],"iteration":79,"passed_time":0.08756345291,"remaining_time":1.006979708},
{"learn":[252512.7011],"iteration":80,"passed_time":0.08851402912,"remaining_time":1.004251762},
{"learn":[251116.4922],"iteration":81,"passed_time":0.08941264608,"remaining_time":1.000985477},
{"learn":[250681.1212],"iteration":82,"passed_time":0.09031234553,"remaining_time":0.997788203},
{"learn":[248815.9533],"iteration":83,"passed_time":0.09115377093,"remaining_time":0.9940101688},
{"learn":[247664.0088],"iteration":84,"passed_time":0.09202308048,"remaining_time":0.9906013958},
{"learn":[246089.5463],"iteration":85,"passed_time":0.09307696959,"remaining_time":0.9892133745},
{"learn":[245719.9491],"iteration":86,"passed_time":0.09402988143,"remaining_time":0.9867733534},
{"learn":[243986.2639],"iteration":87,"passed_time":0.0950384513,"remaining_time":0.9849439498},
{"learn":[242164.8176],"iteration":88,"passed_time":0.09596480205,"remaining_time":0.9822914008},
{"learn":[241317.345],"iteration":89,"passed_time":0.09693860194,"remaining_time":0.9801569752},
{"learn":[239643.6617],"iteration":90,"passed_time":0.09782802776,"remaining_time":0.9772052443},
{"learn":[238315.9064],"iteration":91,"passed_time":0.09872007961,"remaining_time":0.974324264},
{"learn":[236814.0562],"iteration":92,"passed_time":0.09961090866,"remaining_time":0.9714741307},
{"learn":[235699.8249],"iteration":93,"passed_time":0.100500996,"remaining_time":0.9686585359},
{"learn":[234184.6254],"iteration":94,"passed_time":0.1013857811,"remaining_time":0.9658329677},
{"learn":[233281.0895],"iteration":95,"passed_time":0.1023249865,"remaining_time":0.9635602891},
{"learn":[231527.8144],"iteration":96,"passed_time":0.1033738643,"remaining_time":0.962336077},
{"learn":[230692.8749],"iteration":97,"passed_time":0.1042987564,"remaining_time":0.9599742684},
{"learn":[229919.484],"iteration":98,"passed_time":0.1052241149,"remaining_time":0.9576457326},
{"learn":[228883.6375],"iteration":99,"passed_time":0.1061181413,"remaining_time":0.9550632717},
{"learn":[227841.6034],"iteration":100,"passed_time":0.10712826,"remaining_time":0.9535475815},
{"learn":[226939.4039],"iteration":101,"passed_time":0.1080602136,"remaining_time":0.9513536455},
{"learn":[226150.1817],"iteration":102,"passed_time":0.1089232989,"remaining_time":0.9485844571},
{"learn":[225336.8555],"iteration":103,"passed_time":0.1098129046,"remaining_time":0.9460804086},
{"learn":[224295.8475],"iteration":104,"passed_time":0.1107597525,"remaining_time":0.9440950329},
{"learn":[223205.4385],"iteration":105,"passed_time":0.1117123035,"remaining_time":0.942177352},
{"learn":[222126.8236],"iteration":106,"passed_time":0.1125849808,"remaining_time":0.9396111012},
{"learn":[221196.5388],"iteration":107,"passed_time":0.1135495795,"remaining_time":0.9378354158},
{"learn":[220745.7532],"iteration":108,"passed_time":0.1144468333,"remaining_time":0.9355241146},
{"learn":[220129.7508],"iteration":109,"passed_time":0.115348314,"remaining_time":0.9332727221},
{"learn":[218769.9891],"iteration":110,"passed_time":0.1163045165,"remaining_time":0.9314839208},
{"learn":[217881.9357],"iteration":111,"passed_time":0.1172105606,"remaining_time":0.9293123018},
{"learn":[216768.6275],"iteration":112,"passed_time":0.11809287,"remaining_time":0.9269767763},
{"learn":[215868.4684],"iteration":113,"passed_time":0.1189818445,"remaining_time":0.9247185462},
{"learn":[214362.2987],"iteration":114,"passed_time":0.1199037654,"remaining_time":0.9227376726},
{"learn":[213498.9875],"iteration":115,"passed_time":0.1207880293,"remaining_time":0.9204880855},
{"learn":[212668.1118],"iteration":116,"passed_time":0.1216580305,"remaining_time":0.9181541956},
{"learn":[212174.6192],"iteration":117,"passed_time":0.1221655779,"remaining_time":0.9131359296},
{"learn":[210699.9323],"iteration":118,"passed_time":0.1230535504,"remaining_time":0.9110098981},
{"learn":[209904.2182],"iteration":119,"passed_time":0.1235976318,"remaining_time":0.9063826334},
{"learn":[208118.3165],"iteration":120,"passed_time":0.1245616793,"remaining_time":0.9048736868},
{"learn":[207339.5615],"iteration":121,"passed_time":0.1255764635,"remaining_time":0.9037388108},
{"learn":[206691.3407],"iteration":122,"passed_time":0.1265799519,"remaining_time":0.9025253481},
{"learn":[205349.5713],"iteration":123,"passed_time":0.1275044985,"remaining_time":0.9007575861},
{"learn":[204091.5254],"iteration":124,"passed_time":0.1284109936,"remaining_time":0.898876955},
{"learn":[203857.5604],"iteration":125,"passed_time":0.1293501635,"remaining_time":0.897238436},
{"learn":[203294.2623],"iteration":126,"passed_time":0.1302468664,"remaining_time":0.8953190105},
{"learn":[201478.1825],"iteration":127,"passed_time":0.131146225,"remaining_time":0.893433658},
{"learn":[201015.2171],"iteration":128,"passed_time":0.1320538627,"remaining_time":0.8916194918},
{"learn":[200705.4515],"iteration":129,"passed_time":0.1329457743,"remaining_time":0.8897140278},
{"learn":[200500.3226],"iteration":130,"passed_time":0.1338123175,"remaining_time":0.8876557547},
{"learn":[199969.5608],"iteration":131,"passed_time":0.1347426474,"remaining_time":0.8860349841},
{"learn":[198843.7959],"iteration":132,"passed_time":0.1357518988,"remaining_time":0.8849390696},
{"learn":[197852.1634],"iteration":133,"passed_time":0.1367027554,"remaining_time":0.8834670609},
{"learn":[197171.6909],"iteration":134,"passed_time":0.1375759338,"remaining_time":0.8815050575},
{"learn":[196445.028],"iteration":135,"passed_time":0.1384621628,"remaining_time":0.8796419756},
{"learn":[196249.4254],"iteration":136,"passed_time":0.1393594968,"remaining_time":0.8778631077},
{"learn":[194856.841],"iteration":137,"passed_time":0.1403348068,"remaining_time":0.8765840829},
{"learn":[194076.7277],"iteration":138,"passed_time":0.1412006082,"remaining_time":0.8746311058},
{"learn":[193648.832],"iteration":139,"passed_time":0.1421390502,"remaining_time":0.87313988},
{"learn":[192780.4198],"iteration":140,"passed_time":0.1430821996,"remaining_time":0.8716851736},
{"learn":[192401.3111],"iteration":141,"passed_time":0.144013592,"remaining_time":0.8701666331},
{"learn":[191147.093],"iteration":142,"passed_time":0.1448591769,"remaining_time":0.8681420604},
{"learn":[190213.4925],"iteration":143,"passed_time":0.1457251989,"remaining_time":0.8662553492},
{"learn":[188607.3798],"iteration":144,"passed_time":0.1465539752,"remaining_time":0.8641630954},
{"learn":[187774.0421],"iteration":145,"passed_time":0.1474566515,"remaining_time":0.8625204138},
{"learn":[186703.1903],"iteration":146,"passed_time":0.148368769,"remaining_time":0.8609425849},
{"learn":[185744.5621],"iteration":147,"passed_time":0.1492548477,"remaining_time":0.8592238528},
{"learn":[185256.3606],"iteration":148,"passed_time":0.1501135528,"remaining_time":0.857359956},
{"learn":[184317.8514],"iteration":149,"passed_time":0.1510448249,"remaining_time":0.8559206744},
{"learn":[183549.4191],"iteration":150,"passed_time":0.1518966442,"remaining_time":0.8540413969},
{"learn":[182766.5231],"iteration":151,"passed_time":0.1528506686,"remaining_time":0.8527458354},
{"learn":[181729.509],"iteration":152,"passed_time":0.1537321759,"remaining_time":0.8510532878},
{"learn":[180689.5346],"iteration":153,"passed_time":0.154680828,"remaining_time":0.849740133},
{"learn":[180167.7112],"iteration":154,"passed_time":0.1556405154,"remaining_time":0.8484918421},
{"learn":[179536.9431],"iteration":155,"passed_time":0.1565762277,"remaining_time":0.8471175396},
{"learn":[178525.6177],"iteration":156,"passed_time":0.157675516,"remaining_time":0.8466271336},
{"learn":[177432.4526],"iteration":157,"passed_time":0.1586306279,"remaining_time":0.8453606878},
{"learn":[177051.9023],"iteration":158,"passed_time":0.1595723239,"remaining_time":0.8440271976},
{"learn":[175530.0259],"iteration":159,"passed_time":0.1605411724,"remaining_time":0.8428411553},
{"learn":[174746.0353],"iteration":160,"passed_time":0.1614218281,"remaining_time":0.8411982221},
{"learn":[172946.451],"iteration":161,"passed_time":0.1624204907,"remaining_time":0.8401751308},
{"learn":[172274.8782],"iteration":162,"passed_time":0.1634008551,"remaining_time":0.8390583789},
{"learn":[171338.0535],"iteration":163,"passed_time":0.1644039925,"remaining_time":0.8380593765},
{"learn":[170625.3737],"iteration":164,"passed_time":0.1653285043,"remaining_time":0.8366624308},
{"learn":[169980.2264],"iteration":165,"passed_time":0.1664251668,"remaining_time":0.8361360789},
{"learn":[169143.6234],"iteration":166,"passed_time":0.1673783242,"remaining_time":0.8348870902},
{"learn":[168218.1623],"iteration":167,"passed_time":0.1683247712,"remaining_time":0.8336083906},
{"learn":[167499.4334],"iteration":168,"passed_time":0.1692252421,"remaining_time":0.8321075516},
{"learn":[166886.9605],"iteration":169,"passed_time":0.1701370597,"remaining_time":0.8306691739},
{"learn":[166308.6606],"iteration":170,"passed_time":0.1710709475,"remaining_time":0.8293439504},
{"learn":[165399.9349],"iteration":171,"passed_time":0.1720748266,"remaining_time":0.8283602119},
{"learn":[164907.1965],"iteration":172,"passed_time":0.1730809614,"remaining_time":0.8273870236},
{"learn":[163437.2001],"iteration":173,"passed_time":0.1741311768,"remaining_time":0.8266227129},
{"learn":[162488.9134],"iteration":174,"passed_time":0.1751314576,"remaining_time":0.8256197287},
{"learn":[161768.3735],"iteration":175,"passed_time":0.1761099383,"remaining_time":0.824514711},
{"learn":[160964.2391],"iteration":176,"passed_time":0.177163993,"remaining_time":0.8237625212},
{"learn":[159954.0914],"iteration":177,"passed_time":0.1782029723,"remaining_time":0.8229373215},
{"learn":[159390.2224],"iteration":178,"passed_time":0.17911473,"remaining_time":0.8215262198},
{"learn":[158347.8857],"iteration":179,"passed_time":0.1800107009,"remaining_time":0.8200487485},
{"learn":[157642.5202],"iteration":180,"passed_time":0.1809641635,"remaining_time":0.8188378446},
{"learn":[156867.4874],"iteration":181,"passed_time":0.1818646547,"remaining_time":0.81739169},
{"learn":[156343.5128],"iteration":182,"passed_time":0.182719912,"remaining_time":0.8157495523},
{"learn":[155485.5467],"iteration":183,"passed_time":0.1836049577,"remaining_time":0.8142480733},
{"learn":[154483.1418],"iteration":184,"passed_time":0.1845536599,"remaining_time":0.8130336908},
{"learn":[153573.2785],"iteration":185,"passed_time":0.185445832,"remaining_time":0.8115747702},
{"learn":[152473.0097],"iteration":186,"passed_time":0.1863341054,"remaining_time":0.810104961},
{"learn":[151518.1941],"iteration":187,"passed_time":0.187204748,"remaining_time":0.8085651884},
{"learn":[150986.1437],"iteration":188,"passed_time":0.188227811,"remaining_time":0.8076865328},
{"learn":[150489.312],"iteration":189,"passed_time":0.1892007695,"remaining_time":0.806592754},
{"learn":[149791.8016],"iteration":190,"passed_time":0.1901462236,"remaining_time":0.805383743},
{"learn":[149237.993],"iteration":191,"passed_time":0.1912935097,"remaining_time":0.8050268532},
{"learn":[148983.3987],"iteration":192,"passed_time":0.1924297511,"remaining_time":0.8046155914},
{"learn":[148529.7432],"iteration":193,"passed_time":0.1934119358,"remaining_time":0.8035568054},
{"learn":[147732.7968],"iteration":194,"passed_time":0.1944122862,"remaining_time":0.802573797},
{"learn":[147317.6977],"iteration":195,"passed_time":0.1953415743,"remaining_time":0.8012991108},
{"learn":[146492.5944],"iteration":196,"passed_time":0.1962319523,"remaining_time":0.7998693283},
{"learn":[146130.9286],"iteration":197,"passed_time":0.1971434533,"remaining_time":0.7985305534},
{"learn":[145751.0469],"iteration":198,"passed_time":0.1980801429,"remaining_time":0.7972974595},
{"learn":[145185.8812],"iteration":199,"passed_time":0.1990386726,"remaining_time":0.7961546905},
{"learn":[144177.8348],"iteration":200,"passed_time":0.2000631741,"remaining_time":0.7952760007},
{"learn":[143553.4651],"iteration":201,"passed_time":0.2010440002,"remaining_time":0.7942233275},
{"learn":[142805.2404],"iteration":202,"passed_time":0.2020114605,"remaining_time":0.7931188868},
{"learn":[142313.9033],"iteration":203,"passed_time":0.2029501251,"remaining_time":0.7919034293},
{"learn":[141497.764],"iteration":204,"passed_time":0.2039396156,"remaining_time":0.7908877774},
{"learn":[141047.7002],"iteration":205,"passed_time":0.2048781543,"remaining_time":0.789675993},
{"learn":[140317.0861],"iteration":206,"passed_time":0.2060823764,"remaining_time":0.7894846592},
{"learn":[139895.8608],"iteration":207,"passed_time":0.2070932515,"remaining_time":0.7885473808},
{"learn":[139360.6254],"iteration":208,"passed_time":0.2081015708,"remaining_time":0.7875997249},
{"learn":[139134.5731],"iteration":209,"passed_time":0.2091097598,"remaining_time":0.7866510012},
{"learn":[138602.8262],"iteration":210,"passed_time":0.210154984,"remaining_time":0.7858402008},
{"learn":[138089.7625],"iteration":211,"passed_time":0.2111169902,"remaining_time":0.7847178691},
{"learn":[137720.8371],"iteration":212,"passed_time":0.2121663533,"remaining_time":0.7839198126},
{"learn":[137348.6287],"iteration":213,"passed_time":0.2132876295,"remaining_time":0.7833835366},
{"learn":[136845.5262],"iteration":214,"passed_time":0.2142336556,"remaining_time":0.7822019517},
{"learn":[136436.4815],"iteration":215,"passed_time":0.215239242,"remaining_time":0.7812387301},
{"learn":[136020.4497],"iteration":216,"passed_time":0.2162417178,"remaining_time":0.7802638943},
{"learn":[135420.9347],"iteration":217,"passed_time":0.2172148261,"remaining_time":0.7791834589},
{"learn":[134805.0404],"iteration":218,"passed_time":0.218193133,"remaining_time":0.7781225427},
{"learn":[134371.6309],"iteration":219,"passed_time":0.2192980945,"remaining_time":0.7775114261},
{"learn":[134012.2086],"iteration":220,"passed_time":0.2204367014,"remaining_time":0.7770144362},
{"learn":[133693.9793],"iteration":221,"passed_time":0.2214219329,"remaining_time":0.7759741611},
{"learn":[133358.8452],"iteration":222,"passed_time":0.2224541368,"remaining_time":0.7750980463},
{"learn":[132561.0899],"iteration":223,"passed_time":0.2234830788,"remaining_time":0.7742092373},
{"learn":[132318.7814],"iteration":224,"passed_time":0.2244528494,"remaining_time":0.7731153703},
{"learn":[131987.6554],"iteration":225,"passed_time":0.225362176,"remaining_time":0.771815594},
{"learn":[131636.7916],"iteration":226,"passed_time":0.2263143612,"remaining_time":0.7706652036},
{"learn":[130982.0354],"iteration":227,"passed_time":0.227240752,"remaining_time":0.7694292131},
{"learn":[130715.1075],"iteration":228,"passed_time":0.2282246051,"remaining_time":0.7683893908},
{"learn":[130571.7224],"iteration":229,"passed_time":0.2291417293,"remaining_time":0.767126659},
{"learn":[130208.9889],"iteration":230,"passed_time":0.2301647076,"remaining_time":0.766219308},
{"learn":[129910.5155],"iteration":231,"passed_time":0.2311246704,"remaining_time":0.7651023572},
{"learn":[129384.7527],"iteration":232,"passed_time":0.2322230368,"remaining_time":0.7644423572},
{"learn":[128651.3352],"iteration":233,"passed_time":0.2368476346,"remaining_time":0.7753217441},
{"learn":[128108.2724],"iteration":234,"passed_time":0.2379510023,"remaining_time":0.7746064542},
{"learn":[127767.7059],"iteration":235,"passed_time":0.2405203823,"remaining_time":0.7786337798},
{"learn":[127458.7398],"iteration":236,"passed_time":0.2416264767,"remaining_time":0.777894522},
{"learn":[127115.925],"iteration":237,"passed_time":0.2434552526,"remaining_time":0.7794659769},
{"learn":[126954.3514],"iteration":238,"passed_time":0.2447181177,"remaining_time":0.7792070609},
{"learn":[126596.0005],"iteration":239,"passed_time":0.2462946941,"remaining_time":0.7799331979},
{"learn":[125998.4033],"iteration":240,"passed_time":0.2473260666,"remaining_time":0.7789231725},
{"learn":[125759.3562],"iteration":241,"passed_time":0.2483049379,"remaining_time":0.7777485246},
{"learn":[125456.7313],"iteration":242,"passed_time":0.2498370122,"remaining_time":0.7782988405},
{"learn":[125210.9634],"iteration":243,"passed_time":0.2508888817,"remaining_time":0.7773442399},
{"learn":[124452.2868],"iteration":244,"passed_time":0.2522521669,"remaining_time":0.7773485143},
{"learn":[124242.652],"iteration":245,"passed_time":0.2533778963,"remaining_time":0.7766135519},
{"learn":[124053.9125],"iteration":246,"passed_time":0.2545492812,"remaining_time":0.7760146101},
{"learn":[123633.8395],"iteration":247,"passed_time":0.2556876161,"remaining_time":0.7753108358},
{"learn":[123333.7741],"iteration":248,"passed_time":0.2567541725,"remaining_time":0.7743870825},
{"learn":[122886.4445],"iteration":249,"passed_time":0.2577542425,"remaining_time":0.7732627276},
{"learn":[122479.5329],"iteration":250,"passed_time":0.2588603238,"remaining_time":0.7724557073},
{"learn":[121644.1132],"iteration":251,"passed_time":0.2600583727,"remaining_time":0.7719192966},
{"learn":[120969.3555],"iteration":252,"passed_time":0.2612101321,"remaining_time":0.771240983},
{"learn":[120760.3625],"iteration":253,"passed_time":0.2623098314,"remaining_time":0.7704060401},
{"learn":[120281.5096],"iteration":254,"passed_time":0.2634143219,"remaining_time":0.7695830187},
{"learn":[119964.2566],"iteration":255,"passed_time":0.2645738993,"remaining_time":0.7689178949},
{"learn":[119629.3764],"iteration":256,"passed_time":0.2656899119,"remaining_time":0.7681229747},
{"learn":[119377.0863],"iteration":257,"passed_time":0.2667150493,"remaining_time":0.7670642116},
{"learn":[119176.7842],"iteration":258,"passed_time":0.2677819038,"remaining_time":0.7661250606},
{"learn":[118427.9475],"iteration":259,"passed_time":0.2688443874,"remaining_time":0.7651724871},
{"learn":[118038.6368],"iteration":260,"passed_time":0.2698866716,"remaining_time":0.7641618787},
{"learn":[117906.3979],"iteration":261,"passed_time":0.2709044556,"remaining_time":0.7630820161},
{"learn":[117548.3327],"iteration":262,"passed_time":0.2719285612,"remaining_time":0.7620203407},
{"learn":[117194.2103],"iteration":263,"passed_time":0.2728874869,"remaining_time":0.7607772361},
{"learn":[116513.7361],"iteration":264,"passed_time":0.273932457,"remaining_time":0.759774928},
{"learn":[115968.9116],"iteration":265,"passed_time":0.2748610028,"remaining_time":0.7584510379},
{"learn":[115546.1218],"iteration":266,"passed_time":0.2758885896,"remaining_time":0.7574020082},
{"learn":[115347.2925],"iteration":267,"passed_time":0.276839467,"remaining_time":0.7561436189},
{"learn":[115104.4817],"iteration":268,"passed_time":0.2778526475,"remaining_time":0.7550568228},
{"learn":[114921.5993],"iteration":269,"passed_time":0.2788877632,"remaining_time":0.7540298782},
{"learn":[114634.1856],"iteration":270,"passed_time":0.2798299403,"remaining_time":0.7527528653},
{"learn":[114305.2493],"iteration":271,"passed_time":0.2807750743,"remaining_time":0.7514862282},
{"learn":[114130.7819],"iteration":272,"passed_time":0.2817065468,"remaining_time":0.750185566},
{"learn":[113761.635],"iteration":273,"passed_time":0.2825997914,"remaining_time":0.7487863086},
{"learn":[113115.3343],"iteration":274,"passed_time":0.2836726945,"remaining_time":0.7478643764},
{"learn":[112955.5373],"iteration":275,"passed_time":0.2847749602,"remaining_time":0.7470183737},
{"learn":[112779.4701],"iteration":276,"passed_time":0.2859083943,"remaining_time":0.746251874},
{"learn":[112663.7205],"iteration":277,"passed_time":0.2871652484,"remaining_time":0.7458032712},
{"learn":[112340.4548],"iteration":278,"passed_time":0.2881794415,"remaining_time":0.7447217825},
{"learn":[112056.6002],"iteration":279,"passed_time":0.289163505,"remaining_time":0.7435632986},
{"learn":[111914.6398],"iteration":280,"passed_time":0.2900897249,"remaining_time":0.7422580506},
{"learn":[111535.493],"iteration":281,"passed_time":0.2910979693,"remaining_time":0.7411643332},
{"learn":[111272.2252],"iteration":282,"passed_time":0.2922818543,"remaining_time":0.7405162174},
{"learn":[110747.0211],"iteration":283,"passed_time":0.2934640335,"remaining_time":0.739860028},
{"learn":[110569.8158],"iteration":284,"passed_time":0.2945584988,"remaining_time":0.7389800935},
{"learn":[110286.5853],"iteration":285,"passed_time":0.2956023654,"remaining_time":0.7379723388},
{"learn":[110090.2058],"iteration":286,"passed_time":0.2966865136,"remaining_time":0.7370644048},
{"learn":[109653.4689],"iteration":287,"passed_time":0.2977926333,"remaining_time":0.7362095658},
{"learn":[109474.3623],"iteration":288,"passed_time":0.2988525413,"remaining_time":0.7352392971},
{"learn":[109087.374],"iteration":289,"passed_time":0.2998471335,"remaining_time":0.7341084992},
{"learn":[108792.21],"iteration":290,"passed_time":0.3009170795,"remaining_time":0.7331622316},
{"learn":[108487.1942],"iteration":291,"passed_time":0.3019522556,"remaining_time":0.7321308115},
{"learn":[108172.8487],"iteration":292,"passed_time":0.3029642634,"remaining_time":0.7310434614},
{"learn":[107939.1503],"iteration":293,"passed_time":0.3039296494,"remaining_time":0.7298446684},
{"learn":[107712.3683],"iteration":294,"passed_time":0.3048781356,"remaining_time":0.7286070697},
{"learn":[107569.9933],"iteration":295,"passed_time":0.3059777498,"remaining_time":0.7277308645},
{"learn":[107284.8645],"iteration":296,"passed_time":0.3069211899,"remaining_time":0.7264834899},
{"learn":[107064.6207],"iteration":297,"passed_time":0.3078998309,"remaining_time":0.7253210782},
{"learn":[106565.1044],"iteration":298,"passed_time":0.3088934918,"remaining_time":0.7241951095},
{"learn":[106338.8411],"iteration":299,"passed_time":0.3098272245,"remaining_time":0.7229301905},
{"learn":[106094.7273],"iteration":300,"passed_time":0.3107605162,"remaining_time":0.721666448},
{"learn":[105940.093],"iteration":301,"passed_time":0.3116800513,"remaining_time":0.7203730987},
{"learn":[105855.4415],"iteration":302,"passed_time":0.3126148467,"remaining_time":0.7191173207},
{"learn":[105628.4759],"iteration":303,"passed_time":0.3135925,"remaining_time":0.7179617762},
{"learn":[105539.8344],"iteration":304,"passed_time":0.3145053747,"remaining_time":0.7166597883},
{"learn":[105327.8418],"iteration":305,"passed_time":0.315452383,"remaining_time":0.7154377575},
{"learn":[105198.0796],"iteration":306,"passed_time":0.3165462757,"remaining_time":0.7145490848},
{"learn":[104719.095],"iteration":307,"passed_time":0.3175830604,"remaining_time":0.7135307722},
{"learn":[104394.1545],"iteration":308,"passed_time":0.3185460122,"remaining_time":0.7123472312},
{"learn":[103956.3983],"iteration":309,"passed_time":0.3195403124,"remaining_time":0.7112348889},
{"learn":[103826.0272],"iteration":310,"passed_time":0.3204584047,"remaining_time":0.7099544722},
{"learn":[103466.9416],"iteration":311,"passed_time":0.3213612714,"remaining_time":0.7086428037},
{"learn":[103062.1818],"iteration":312,"passed_time":0.322258425,"remaining_time":0.7073212076},
{"learn":[102958.1959],"iteration":313,"passed_time":0.3232074677,"remaining_time":0.7061156779},
{"learn":[102768.0437],"iteration":314,"passed_time":0.3240952397,"remaining_time":0.7047785372},
{"learn":[102573.243],"iteration":315,"passed_time":0.3249614421,"remaining_time":0.7033975519},
{"learn":[102350.1057],"iteration":316,"passed_time":0.3259086909,"remaining_time":0.7021944351},
{"learn":[101998.1972],"iteration":317,"passed_time":0.3268274141,"remaining_time":0.7009317498},
{"learn":[101456.4623],"iteration":318,"passed_time":0.3277128107,"remaining_time":0.6996000755},
{"learn":[101304.934],"iteration":319,"passed_time":0.3285952504,"remaining_time":0.6982649072},
{"learn":[101135.9552],"iteration":320,"passed_time":0.3295049326,"remaining_time":0.6969901845},
{"learn":[100963.1006],"iteration":321,"passed_time":0.3304180629,"remaining_time":0.6957249896},
{"learn":[100703.1886],"iteration":322,"passed_time":0.3313526197,"remaining_time":0.6945068839},
{"learn":[100542.1639],"iteration":323,"passed_time":0.3322902263,"remaining_time":0.6932968919},
{"learn":[100128.5326],"iteration":324,"passed_time":0.3332380464,"remaining_time":0.6921097887},
{"learn":[99592.53748],"iteration":325,"passed_time":0.3342180039,"remaining_time":0.690990597},
{"learn":[99426.92932],"iteration":326,"passed_time":0.3350840159,"remaining_time":0.6896377452},
{"learn":[99140.36544],"iteration":327,"passed_time":0.3360497369,"remaining_time":0.6884921439},
{"learn":[98934.62312],"iteration":328,"passed_time":0.3370117798,"remaining_time":0.6873401344},
{"learn":[98778.03106],"iteration":329,"passed_time":0.3379619152,"remaining_time":0.6861651006},
{"learn":[98644.29143],"iteration":330,"passed_time":0.3388031903,"remaining_time":0.6847714027},
{"learn":[98539.66609],"iteration":331,"passed_time":0.3397253617,"remaining_time":0.6835438},
{"learn":[98424.44645],"iteration":332,"passed_time":0.340595884,"remaining_time":0.6822145785},
{"learn":[98281.46234],"iteration":333,"passed_time":0.3415566434,"remaining_time":0.6810680374},
{"learn":[97934.26967],"iteration":334,"passed_time":0.3425026594,"remaining_time":0.6798933388},
{"learn":[97784.08356],"iteration":335,"passed_time":0.3434264242,"remaining_time":0.6786760287},
{"learn":[97465.10124],"iteration":336,"passed_time":0.3443854005,"remaining_time":0.6775297345},
{"learn":[97095.22156],"iteration":337,"passed_time":0.3452674293,"remaining_time":0.6762338408},
{"learn":[96972.78081],"iteration":338,"passed_time":0.3461510884,"remaining_time":0.6749435677},
{"learn":[96868.30305],"iteration":339,"passed_time":0.3472104984,"remaining_time":0.6739968498},
{"learn":[96669.3333],"iteration":340,"passed_time":0.3483019486,"remaining_time":0.6731113905},
{"learn":[96588.34054],"iteration":341,"passed_time":0.3494255502,"remaining_time":0.6722865849},
{"learn":[96363.68953],"iteration":342,"passed_time":0.3503997009,"remaining_time":0.6711737711},
{"learn":[96278.33191],"iteration":343,"passed_time":0.3513044921,"remaining_time":0.6699294965},
{"learn":[95791.90322],"iteration":344,"passed_time":0.3522120095,"remaining_time":0.6686923658},
{"learn":[95712.54023],"iteration":345,"passed_time":0.3530980375,"remaining_time":0.6674165217},
{"learn":[95567.71758],"iteration":346,"passed_time":0.3540039913,"remaining_time":0.6661804217},
{"learn":[95443.94824],"iteration":347,"passed_time":0.3549462618,"remaining_time":0.6650142607},
{"learn":[95124.76801],"iteration":348,"passed_time":0.3558510731,"remaining_time":0.6637795088},
{"learn":[95056.49694],"iteration":349,"passed_time":0.3567999356,"remaining_time":0.6626284518},
{"learn":[94863.35656],"iteration":350,"passed_time":0.3577244621,"remaining_time":0.6614335496},
{"learn":[94758.92549],"iteration":351,"passed_time":0.3586669603,"remaining_time":0.6602732678},
{"learn":[94631.31129],"iteration":352,"passed_time":0.3595855126,"remaining_time":0.6590703304},
{"learn":[94408.62694],"iteration":353,"passed_time":0.3604716508,"remaining_time":0.6578098487},
{"learn":[94302.81635],"iteration":354,"passed_time":0.3614128758,"remaining_time":0.6566515631},
{"learn":[94206.93471],"iteration":355,"passed_time":0.3623783368,"remaining_time":0.6555383395},
{"learn":[94081.4387],"iteration":356,"passed_time":0.3633650361,"remaining_time":0.6544641966},
{"learn":[93952.88825],"iteration":357,"passed_time":0.3643374528,"remaining_time":0.6533649293},
{"learn":[93564.38073],"iteration":358,"passed_time":0.3652873548,"remaining_time":0.6522261683},
{"learn":[93127.23672],"iteration":359,"passed_time":0.3662544021,"remaining_time":0.651118937},
{"learn":[93032.73801],"iteration":360,"passed_time":0.3672951512,"remaining_time":0.6501429408},
{"learn":[92786.16139],"iteration":361,"passed_time":0.36829685,"remaining_time":0.6490977633},
{"learn":[92571.82963],"iteration":362,"passed_time":0.3692500926,"remaining_time":0.6479677934},
{"learn":[92460.42424],"iteration":363,"passed_time":0.3701912975,"remaining_time":0.6468177616},
{"learn":[92354.46489],"iteration":364,"passed_time":0.3711650273,"remaining_time":0.6457254584},
{"learn":[92275.04378],"iteration":365,"passed_time":0.372066581,"remaining_time":0.6445087769},
{"learn":[92017.25222],"iteration":366,"passed_time":0.3729883712,"remaining_time":0.6433287166},
{"learn":[91863.52951],"iteration":367,"passed_time":0.3738808541,"remaining_time":0.6420997276},
{"learn":[91767.965],"iteration":368,"passed_time":0.3748572098,"remaining_time":0.6410159876},
{"learn":[91381.57211],"iteration":369,"passed_time":0.3758598561,"remaining_time":0.6399775928},
{"learn":[91222.39362],"iteration":370,"passed_time":0.3771020834,"remaining_time":0.6393455808},
{"learn":[91128.69966],"iteration":371,"passed_time":0.3782167673,"remaining_time":0.6384949728},
{"learn":[90976.58267],"iteration":372,"passed_time":0.3791992973,"remaining_time":0.6374208027},
{"learn":[90835.74508],"iteration":373,"passed_time":0.3803027454,"remaining_time":0.6365495151},
{"learn":[90695.76844],"iteration":374,"passed_time":0.3815583535,"remaining_time":0.6359305892},
{"learn":[90560.71622],"iteration":375,"passed_time":0.3824931286,"remaining_time":0.6347758305},
{"learn":[90451.51031],"iteration":376,"passed_time":0.383435391,"remaining_time":0.6336346116},
{"learn":[90247.84696],"iteration":377,"passed_time":0.3844128042,"remaining_time":0.6325522863},
{"learn":[89854.55708],"iteration":378,"passed_time":0.3853984814,"remaining_time":0.6314840553},
{"learn":[89763.85245],"iteration":379,"passed_time":0.3863928436,"remaining_time":0.630430429},
{"learn":[89630.37034],"iteration":380,"passed_time":0.3874757795,"remaining_time":0.6295210171},
{"learn":[89416.7697],"iteration":381,"passed_time":0.3885327763,"remaining_time":0.6285687323},
{"learn":[89224.09404],"iteration":382,"passed_time":0.3895038644,"remaining_time":0.6274775048},
{"learn":[89128.68562],"iteration":383,"passed_time":0.3904556537,"remaining_time":0.6263559444},
{"learn":[88938.78162],"iteration":384,"passed_time":0.391480443,"remaining_time":0.6253518764},
{"learn":[88815.16756],"iteration":385,"passed_time":0.3924453223,"remaining_time":0.6242524039},
{"learn":[88587.26528],"iteration":386,"passed_time":0.393457203,"remaining_time":0.623228076},
{"learn":[88470.14976],"iteration":387,"passed_time":0.3944565216,"remaining_time":0.6221839979},
{"learn":[88389.07924],"iteration":388,"passed_time":0.3954242578,"remaining_time":0.6210905437},
{"learn":[88179.11947],"iteration":389,"passed_time":0.3964217867,"remaining_time":0.6200443331},
{"learn":[88115.77948],"iteration":390,"passed_time":0.3974657881,"remaining_time":0.6190707543},
{"learn":[87907.24325],"iteration":391,"passed_time":0.3984235962,"remaining_time":0.6179631288},
{"learn":[87810.14451],"iteration":392,"passed_time":0.3993970505,"remaining_time":0.6168804317},
{"learn":[87607.61148],"iteration":393,"passed_time":0.4003835697,"remaining_time":0.6158183838},
{"learn":[87474.43435],"iteration":394,"passed_time":0.4014142203,"remaining_time":0.6148243122},
{"learn":[87360.21397],"iteration":395,"passed_time":0.4023631029,"remaining_time":0.6137053388},
{"learn":[87257.48043],"iteration":396,"passed_time":0.4032735218,"remaining_time":0.6125288},
{"learn":[87184.03297],"iteration":397,"passed_time":0.4042873289,"remaining_time":0.6115099799},
{"learn":[87107.54746],"iteration":398,"passed_time":0.4053705104,"remaining_time":0.6105956811},
{"learn":[86788.05392],"iteration":399,"passed_time":0.4063651382,"remaining_time":0.6095477073},
{"learn":[86693.4378],"iteration":400,"passed_time":0.4073766897,"remaining_time":0.6085252796},
{"learn":[86607.25059],"iteration":401,"passed_time":0.4082547496,"remaining_time":0.607304329},
{"learn":[86524.59545],"iteration":402,"passed_time":0.4092181756,"remaining_time":0.6062115406},
{"learn":[86398.31041],"iteration":403,"passed_time":0.4102433437,"remaining_time":0.6052104773},
{"learn":[86319.66685],"iteration":404,"passed_time":0.4112234982,"remaining_time":0.604143164},
{"learn":[86245.9571],"iteration":405,"passed_time":0.4122131844,"remaining_time":0.6030902254},
{"learn":[86084.31923],"iteration":406,"passed_time":0.4132885281,"remaining_time":0.6021624009},
{"learn":[86014.35746],"iteration":407,"passed_time":0.414301894,"remaining_time":0.6011439246},
{"learn":[85814.61924],"iteration":408,"passed_time":0.4152168485,"remaining_time":0.5999832701},
{"learn":[85467.67455],"iteration":409,"passed_time":0.4161609601,"remaining_time":0.5988657719},
{"learn":[85132.03914],"iteration":410,"passed_time":0.4170940213,"remaining_time":0.5977332811},
{"learn":[84974.72081],"iteration":411,"passed_time":0.418193385,"remaining_time":0.5968391029},
{"learn":[84811.65707],"iteration":412,"passed_time":0.4191206729,"remaining_time":0.5956993584},
{"learn":[84712.2055],"iteration":413,"passed_time":0.4202195806,"remaining_time":0.5948035609},
{"learn":[84633.30647],"iteration":414,"passed_time":0.4211998654,"remaining_time":0.5937395693},
{"learn":[84514.76977],"iteration":415,"passed_time":0.4222008676,"remaining_time":0.5927050641},
{"learn":[84402.18164],"iteration":416,"passed_time":0.4231508377,"remaining_time":0.5915993726},
{"learn":[84255.69954],"iteration":417,"passed_time":0.4241609967,"remaining_time":0.5905782299},
{"learn":[84175.86205],"iteration":418,"passed_time":0.4251601995,"remaining_time":0.5895419473},
{"learn":[84098.47437],"iteration":419,"passed_time":0.4261245777,"remaining_time":0.5884577502},
{"learn":[84013.4308],"iteration":420,"passed_time":0.4271316742,"remaining_time":0.5874328726},
{"learn":[83895.36323],"iteration":421,"passed_time":0.428054322,"remaining_time":0.5862924125},
{"learn":[83806.37618],"iteration":422,"passed_time":0.4290245784,"remaining_time":0.5852179238},
{"learn":[83690.66842],"iteration":423,"passed_time":0.4299467844,"remaining_time":0.5840786505},
{"learn":[83623.07625],"iteration":424,"passed_time":0.4309009343,"remaining_time":0.5829836171},
{"learn":[83528.43529],"iteration":425,"passed_time":0.4318954271,"remaining_time":0.5819436036},
{"learn":[83441.44136],"iteration":426,"passed_time":0.4330354258,"remaining_time":0.5810990609},
{"learn":[83355.91707],"iteration":427,"passed_time":0.4340189616,"remaining_time":0.5800440327},
{"learn":[83105.50146],"iteration":428,"passed_time":0.4350218449,"remaining_time":0.5790150896},
{"learn":[82963.71824],"iteration":429,"passed_time":0.4359749672,"remaining_time":0.5779203054},
{"learn":[82827.09865],"iteration":430,"passed_time":0.4369147489,"remaining_time":0.5768085664},
{"learn":[82698.58398],"iteration":431,"passed_time":0.437894302,"remaining_time":0.5757499156},
{"learn":[82571.27415],"iteration":432,"passed_time":0.4389553157,"remaining_time":0.5747983002},
{"learn":[82440.67545],"iteration":433,"passed_time":0.4399177191,"remaining_time":0.5737175783},
{"learn":[82364.05115],"iteration":434,"passed_time":0.4409050601,"remaining_time":0.5726697907},
{"learn":[82113.23402],"iteration":435,"passed_time":0.4419069647,"remaining_time":0.5716411194},
{"learn":[82041.5026],"iteration":436,"passed_time":0.442962688,"remaining_time":0.5706819069},
{"learn":[81807.53901],"iteration":437,"passed_time":0.4439767856,"remaining_time":0.5696688436},
{"learn":[81611.05311],"iteration":438,"passed_time":0.4449167323,"remaining_time":0.5685610178},
{"learn":[81529.23541],"iteration":439,"passed_time":0.4459418102,"remaining_time":0.5675623038},
{"learn":[81482.5149],"iteration":440,"passed_time":0.44688514,"remaining_time":0.5664598486},
{"learn":[81401.61098],"iteration":441,"passed_time":0.4479534673,"remaining_time":0.5655159157},
{"learn":[81311.42602],"iteration":442,"passed_time":0.4489335221,"remaining_time":0.564460433},
{"learn":[81250.0531],"iteration":443,"passed_time":0.4498726723,"remaining_time":0.5633540671},
{"learn":[81084.02189],"iteration":444,"passed_time":0.4508546254,"remaining_time":0.5623018362},
{"learn":[80894.29913],"iteration":445,"passed_time":0.451907848,"remaining_time":0.5613384479},
{"learn":[80776.6228],"iteration":446,"passed_time":0.4529574074,"remaining_time":0.5603701259},
{"learn":[80702.88243],"iteration":447,"passed_time":0.453969681,"remaining_time":0.5593554998},
{"learn":[80622.20456],"iteration":448,"passed_time":0.4550263465,"remaining_time":0.5583953607},
{"learn":[80554.53157],"iteration":449,"passed_time":0.4560496553,"remaining_time":0.5573940231},
{"learn":[80425.8603],"iteration":450,"passed_time":0.4569492144,"remaining_time":0.5562419484},
{"learn":[80297.05144],"iteration":451,"passed_time":0.4579130313,"remaining_time":0.5551688964},
{"learn":[80205.93464],"iteration":452,"passed_time":0.4589105706,"remaining_time":0.5541370466},
{"learn":[80097.82793],"iteration":453,"passed_time":0.4598300307,"remaining_time":0.5530114467},
{"learn":[79980.88735],"iteration":454,"passed_time":0.460767056,"remaining_time":0.5519077924},
{"learn":[79835.25617],"iteration":455,"passed_time":0.4616876937,"remaining_time":0.5507853187},
{"learn":[79757.62193],"iteration":456,"passed_time":0.4626452409,"remaining_time":0.5497075838},
{"learn":[79673.43279],"iteration":457,"passed_time":0.4634905953,"remaining_time":0.5484976041},
{"learn":[79518.20634],"iteration":458,"passed_time":0.4643984288,"remaining_time":0.5473628539},
{"learn":[79361.33211],"iteration":459,"passed_time":0.4652970858,"remaining_time":0.5462183181},
{"learn":[79223.9055],"iteration":460,"passed_time":0.4662265437,"remaining_time":0.5451108613},
{"learn":[79131.71024],"iteration":461,"passed_time":0.4672219533,"remaining_time":0.5440809759},
{"learn":[79069.69506],"iteration":462,"passed_time":0.4681140152,"remaining_time":0.542931374},
{"learn":[79029.05354],"iteration":463,"passed_time":0.4690356799,"remaining_time":0.5418170785},
{"learn":[78890.09337],"iteration":464,"passed_time":0.4699261982,"remaining_time":0.5406677765},
{"learn":[78762.6417],"iteration":465,"passed_time":0.4708245345,"remaining_time":0.5395285439},
{"learn":[78691.63469],"iteration":466,"passed_time":0.4718097006,"remaining_time":0.5384894441},
{"learn":[78569.11973],"iteration":467,"passed_time":0.4727484498,"remaining_time":0.5373978105},
{"learn":[78399.18457],"iteration":468,"passed_time":0.4737879108,"remaining_time":0.5364208542},
{"learn":[78291.63674],"iteration":469,"passed_time":0.474810433,"remaining_time":0.5354245308},
{"learn":[78194.8447],"iteration":470,"passed_time":0.4757754524,"remaining_time":0.5343635124},
{"learn":[78118.90828],"iteration":471,"passed_time":0.4767114155,"remaining_time":0.533270397},
{"learn":[77989.47747],"iteration":472,"passed_time":0.4776074465,"remaining_time":0.5321334552},
{"learn":[77885.82289],"iteration":473,"passed_time":0.4785689384,"remaining_time":0.5310701721},
{"learn":[77732.9466],"iteration":474,"passed_time":0.4794536734,"remaining_time":0.5299224811},
{"learn":[77629.75063],"iteration":475,"passed_time":0.4803943471,"remaining_time":0.5288374746},
{"learn":[77505.02883],"iteration":476,"passed_time":0.4813314025,"remaining_time":0.5277491059},
{"learn":[77410.64143],"iteration":477,"passed_time":0.4822451142,"remaining_time":0.5266358778},
{"learn":[77353.55429],"iteration":478,"passed_time":0.4831121485,"remaining_time":0.5254727126},
{"learn":[77271.31664],"iteration":479,"passed_time":0.4840234042,"remaining_time":0.5243586879},
{"learn":[77130.92467],"iteration":480,"passed_time":0.4849678036,"remaining_time":0.5232812683},
{"learn":[76960.69775],"iteration":481,"passed_time":0.4859668851,"remaining_time":0.5222631669},
{"learn":[76921.93485],"iteration":482,"passed_time":0.4869136428,"remaining_time":0.5211891373},
{"learn":[76844.25778],"iteration":483,"passed_time":0.4878412765,"remaining_time":0.5200952452},
{"learn":[76758.6532],"iteration":484,"passed_time":0.4887160285,"remaining_time":0.518945886},
{"learn":[76667.86255],"iteration":485,"passed_time":0.4895973758,"remaining_time":0.517804632},
{"learn":[76613.19003],"iteration":486,"passed_time":0.4905591783,"remaining_time":0.5167491961},
{"learn":[76529.03613],"iteration":487,"passed_time":0.4914437229,"remaining_time":0.5156130863},
{"learn":[76464.01369],"iteration":488,"passed_time":0.4923682993,"remaining_time":0.5145198383},
{"learn":[76361.80821],"iteration":489,"passed_time":0.4932588577,"remaining_time":0.5133918723},
{"learn":[76297.39901],"iteration":490,"passed_time":0.4941185151,"remaining_time":0.5122328395},
{"learn":[76254.23517],"iteration":491,"passed_time":0.4950126818,"remaining_time":0.5111106552},
{"learn":[76159.00456],"iteration":492,"passed_time":0.4959963444,"remaining_time":0.5100814333},
{"learn":[76109.33505],"iteration":493,"passed_time":0.4968455176,"remaining_time":0.5089146395},
{"learn":[76037.41234],"iteration":494,"passed_time":0.4977984498,"remaining_time":0.5078549841},
{"learn":[75981.71596],"iteration":495,"passed_time":0.4987073005,"remaining_time":0.5067509667},
{"learn":[75750.54527],"iteration":496,"passed_time":0.499627241,"remaining_time":0.5056589582},
{"learn":[75643.25509],"iteration":497,"passed_time":0.5005814358,"remaining_time":0.5046021702},
{"learn":[75550.90378],"iteration":498,"passed_time":0.5014470669,"remaining_time":0.5034568748},
{"learn":[75478.50749],"iteration":499,"passed_time":0.502368346,"remaining_time":0.502368346},
{"learn":[75393.95647],"iteration":500,"passed_time":0.5032872496,"remaining_time":0.5012781189},
{"learn":[75255.39152],"iteration":501,"passed_time":0.5042674141,"remaining_time":0.5002493471},
{"learn":[75157.81473],"iteration":502,"passed_time":0.5052078523,"remaining_time":0.4991815161},
{"learn":[75013.12582],"iteration":503,"passed_time":0.5061907233,"remaining_time":0.4981559499},
{"learn":[74914.3484],"iteration":504,"passed_time":0.5072741356,"remaining_time":0.4972291032},
{"learn":[74834.99893],"iteration":505,"passed_time":0.5082616372,"remaining_time":0.4962080016},
{"learn":[74777.02908],"iteration":506,"passed_time":0.5091820942,"remaining_time":0.4951218391},
{"learn":[74694.93922],"iteration":507,"passed_time":0.5101908642,"remaining_time":0.4941218606},
{"learn":[74626.49912],"iteration":508,"passed_time":0.5111986027,"remaining_time":0.4931208525},
{"learn":[74503.1339],"iteration":509,"passed_time":0.5121432055,"remaining_time":0.4920591582},
{"learn":[74442.46049],"iteration":510,"passed_time":0.5131013388,"remaining_time":0.4910108702},
{"learn":[74326.11087],"iteration":511,"passed_time":0.5141371785,"remaining_time":0.4900369982},
{"learn":[74262.14568],"iteration":512,"passed_time":0.5150944332,"remaining_time":0.4889882826},
{"learn":[74223.26203],"iteration":513,"passed_time":0.5160149458,"remaining_time":0.4879051822},
{"learn":[74148.34914],"iteration":514,"passed_time":0.5170497708,"remaining_time":0.4869303667},
{"learn":[74078.26317],"iteration":515,"passed_time":0.5180485632,"remaining_time":0.4859215205},
{"learn":[73983.77191],"iteration":516,"passed_time":0.519088425,"remaining_time":0.4849510818},
{"learn":[73909.5046],"iteration":517,"passed_time":0.5200310833,"remaining_time":0.4838899269},
{"learn":[73833.78306],"iteration":518,"passed_time":0.5209106264,"remaining_time":0.4827707346},
{"learn":[73749.45763],"iteration":519,"passed_time":0.5219100673,"remaining_time":0.4817631391},
{"learn":[73661.63754],"iteration":520,"passed_time":0.5228802418,"remaining_time":0.4807286676},
{"learn":[73589.08491],"iteration":521,"passed_time":0.5238980901,"remaining_time":0.4797380978},
{"learn":[73524.83217],"iteration":522,"passed_time":0.5248080864,"remaining_time":0.4786490577},
{"learn":[73442.8888],"iteration":523,"passed_time":0.5258348212,"remaining_time":0.477666746},
{"learn":[73397.07281],"iteration":524,"passed_time":0.5267968107,"remaining_time":0.4766256859},
{"learn":[73329.3882],"iteration":525,"passed_time":0.5277376577,"remaining_time":0.4755658741},
{"learn":[73279.59712],"iteration":526,"passed_time":0.5287373443,"remaining_time":0.4745593242},
{"learn":[73200.60078],"iteration":527,"passed_time":0.529830993,"remaining_time":0.4736367968},
{"learn":[73006.08415],"iteration":528,"passed_time":0.5307440832,"remaining_time":0.4725528605},
{"learn":[72937.30612],"iteration":529,"passed_time":0.5316314644,"remaining_time":0.4714467703},
{"learn":[72891.85435],"iteration":530,"passed_time":0.532582993,"remaining_time":0.4703981614},
{"learn":[72793.14627],"iteration":531,"passed_time":0.5334776709,"remaining_time":0.469299906},
{"learn":[72713.82469],"iteration":532,"passed_time":0.5344519065,"remaining_time":0.4682721207},
{"learn":[72653.21699],"iteration":533,"passed_time":0.5355157135,"remaining_time":0.4673227013},
{"learn":[72608.71349],"iteration":534,"passed_time":0.5364731906,"remaining_time":0.4662804366},
{"learn":[72503.53045],"iteration":535,"passed_time":0.5375031968,"remaining_time":0.4653012749},
{"learn":[72432.82107],"iteration":536,"passed_time":0.5385215223,"remaining_time":0.4643118526},
{"learn":[72332.69839],"iteration":537,"passed_time":0.5395452417,"remaining_time":0.4633269548},
{"learn":[72268.28436],"iteration":538,"passed_time":0.5404410021,"remaining_time":0.4622324712},
{"learn":[72198.87016],"iteration":539,"passed_time":0.5414233918,"remaining_time":0.4612125189},
{"learn":[72158.33396],"iteration":540,"passed_time":0.5423871586,"remaining_time":0.4601769053},
{"learn":[72105.35359],"iteration":541,"passed_time":0.543351186,"remaining_time":0.4591417771},
{"learn":[72017.21911],"iteration":542,"passed_time":0.5443174836,"remaining_time":0.4581088214},
{"learn":[71964.70334],"iteration":543,"passed_time":0.5451858761,"remaining_time":0.4569940432},
{"learn":[71833.33897],"iteration":544,"passed_time":0.5461216039,"remaining_time":0.4559363849},
{"learn":[71770.01545],"iteration":545,"passed_time":0.5471110197,"remaining_time":0.4549238149},
{"learn":[71692.18844],"iteration":546,"passed_time":0.5479800687,"remaining_time":0.4538116474},
{"learn":[71571.67523],"iteration":547,"passed_time":0.5489937448,"remaining_time":0.4528196581},
{"learn":[71501.68052],"iteration":548,"passed_time":0.5499855761,"remaining_time":0.4518096445},
{"learn":[71428.81335],"iteration":549,"passed_time":0.5508962558,"remaining_time":0.4507333002},
{"learn":[71340.66386],"iteration":550,"passed_time":0.551819309,"remaining_time":0.4496676402},
{"learn":[71256.07306],"iteration":551,"passed_time":0.5526982307,"remaining_time":0.44856668},
{"learn":[71103.30901],"iteration":552,"passed_time":0.5536440662,"remaining_time":0.4475206105},
{"learn":[70991.5955],"iteration":553,"passed_time":0.5545750727,"remaining_time":0.4464629646},
{"learn":[70918.23464],"iteration":554,"passed_time":0.5555505264,"remaining_time":0.445441413},
{"learn":[70792.92723],"iteration":555,"passed_time":0.556502456,"remaining_time":0.4444012418},
{"learn":[70740.93195],"iteration":556,"passed_time":0.5574301799,"remaining_time":0.4433421359},
{"learn":[70707.08759],"iteration":557,"passed_time":0.5583919922,"remaining_time":0.4423105028},
{"learn":[70672.49808],"iteration":558,"passed_time":0.5593904844,"remaining_time":0.4413080566},
{"learn":[70608.12635],"iteration":559,"passed_time":0.5603512543,"remaining_time":0.4402759855},
{"learn":[70559.17148],"iteration":560,"passed_time":0.561350387,"remaining_time":0.4392741887},
{"learn":[70525.58344],"iteration":561,"passed_time":0.562465968,"remaining_time":0.4383631565},
{"learn":[70435.71536],"iteration":562,"passed_time":0.5634030906,"remaining_time":0.4373128785},
{"learn":[70381.25185],"iteration":563,"passed_time":0.5644225286,"remaining_time":0.4363266356},
{"learn":[70263.2341],"iteration":564,"passed_time":0.5653248942,"remaining_time":0.4352501398},
{"learn":[70216.77689],"iteration":565,"passed_time":0.5662882804,"remaining_time":0.4342210489},
{"learn":[70153.15724],"iteration":566,"passed_time":0.5672296858,"remaining_time":0.4331754038},
{"learn":[70075.53418],"iteration":567,"passed_time":0.5682868973,"remaining_time":0.4322182036},
{"learn":[70030.52195],"iteration":568,"passed_time":0.5694706197,"remaining_time":0.43135648},
{"learn":[69957.55778],"iteration":569,"passed_time":0.5705856141,"remaining_time":0.4304417791},
{"learn":[69884.64865],"iteration":570,"passed_time":0.5715292549,"remaining_time":0.4293976364},
{"learn":[69806.12697],"iteration":571,"passed_time":0.5724887817,"remaining_time":0.4283657318},
{"learn":[69724.70725],"iteration":572,"passed_time":0.5734943452,"remaining_time":0.4273683864},
{"learn":[69607.9423],"iteration":573,"passed_time":0.5744014517,"remaining_time":0.4262979415},
{"learn":[69497.73959],"iteration":574,"passed_time":0.5753832043,"remaining_time":0.425283238},
{"learn":[69453.55815],"iteration":575,"passed_time":0.5766489357,"remaining_time":0.4244776888},
{"learn":[69388.80897],"iteration":576,"passed_time":0.5777154188,"remaining_time":0.4235244751},
{"learn":[69313.37815],"iteration":577,"passed_time":0.5787646672,"remaining_time":0.4225582865},
{"learn":[69244.96685],"iteration":578,"passed_time":0.5797254522,"remaining_time":0.4215274877},
{"learn":[69209.33134],"iteration":579,"passed_time":0.580738658,"remaining_time":0.4205348903},
{"learn":[69151.02818],"iteration":580,"passed_time":0.5817690377,"remaining_time":0.4195546073},
{"learn":[69062.53869],"iteration":581,"passed_time":0.5827893697,"remaining_time":0.4185669356},
{"learn":[69006.21932],"iteration":582,"passed_time":0.583718146,"remaining_time":0.4175136653},
{"learn":[68972.06408],"iteration":583,"passed_time":0.5846510819,"remaining_time":0.4164637844},
{"learn":[68920.17473],"iteration":584,"passed_time":0.5856250171,"remaining_time":0.4154433882},
{"learn":[68867.62336],"iteration":585,"passed_time":0.5866675121,"remaining_time":0.414471587},
{"learn":[68794.32813],"iteration":586,"passed_time":0.5878481008,"remaining_time":0.4135967046},
{"learn":[68750.08441],"iteration":587,"passed_time":0.588908445,"remaining_time":0.4126365295},
{"learn":[68727.94243],"iteration":588,"passed_time":0.5899339185,"remaining_time":0.4116516817},
{"learn":[68653.99874],"iteration":589,"passed_time":0.5909476703,"remaining_time":0.4106585505},
{"learn":[68545.9525],"iteration":590,"passed_time":0.5919792834,"remaining_time":0.4096777105},
{"learn":[68507.34006],"iteration":591,"passed_time":0.5930123747,"remaining_time":0.4086977177},
{"learn":[68481.82163],"iteration":592,"passed_time":0.5941292292,"remaining_time":0.4077750359},
{"learn":[68381.8646],"iteration":593,"passed_time":0.5952486941,"remaining_time":0.4068534845},
{"learn":[68323.93652],"iteration":594,"passed_time":0.5963856894,"remaining_time":0.4059432003},
{"learn":[68263.93747],"iteration":595,"passed_time":0.5974557852,"remaining_time":0.4049868074},
{"learn":[68176.1893],"iteration":596,"passed_time":0.598473456,"remaining_time":0.4039946445},
{"learn":[68107.96847],"iteration":597,"passed_time":0.5996059079,"remaining_time":0.4030795568},
{"learn":[68041.46819],"iteration":598,"passed_time":0.6006916532,"remaining_time":0.4021324757},
{"learn":[68002.15666],"iteration":599,"passed_time":0.601834542,"remaining_time":0.401223028},
{"learn":[67952.61955],"iteration":600,"passed_time":0.6028572043,"remaining_time":0.4002329859},
{"learn":[67916.5678],"iteration":601,"passed_time":0.6038580018,"remaining_time":0.3992283799},
{"learn":[67863.3212],"iteration":602,"passed_time":0.6049321673,"remaining_time":0.3982720903},
{"learn":[67772.42377],"iteration":603,"passed_time":0.6059978288,"remaining_time":0.3973098348},
{"learn":[67716.12813],"iteration":604,"passed_time":0.6070325084,"remaining_time":0.3963270096},
{"learn":[67642.14168],"iteration":605,"passed_time":0.6081592952,"remaining_time":0.3954038982},
{"learn":[67578.5302],"iteration":606,"passed_time":0.6092363576,"remaining_time":0.3944479218},
{"learn":[67481.26793],"iteration":607,"passed_time":0.6103670932,"remaining_time":0.3935261522},
{"learn":[67408.74368],"iteration":608,"passed_time":0.6113915697,"remaining_time":0.3925354741},
{"learn":[67377.75652],"iteration":609,"passed_time":0.6123956943,"remaining_time":0.3915316734},
{"learn":[67331.36933],"iteration":610,"passed_time":0.6135209043,"remaining_time":0.390604962},
{"learn":[67275.12943],"iteration":611,"passed_time":0.6146364938,"remaining_time":0.3896715026},
{"learn":[67246.50196],"iteration":612,"passed_time":0.6156531066,"remaining_time":0.3886749629},
{"learn":[67132.73511],"iteration":613,"passed_time":0.616711236,"remaining_time":0.3877044578},
{"learn":[67092.93038],"iteration":614,"passed_time":0.617722256,"remaining_time":0.3867041765},
{"learn":[67054.57245],"iteration":615,"passed_time":0.6187457351,"remaining_time":0.3857116271},
{"learn":[66977.03802],"iteration":616,"passed_time":0.6198215898,"remaining_time":0.3847514893},
{"learn":[66920.09437],"iteration":617,"passed_time":0.6208996241,"remaining_time":0.3837923243},
{"learn":[66844.67098],"iteration":618,"passed_time":0.6219482111,"remaining_time":0.3828146501},
{"learn":[66826.30149],"iteration":619,"passed_time":0.623008741,"remaining_time":0.381844067},
{"learn":[66767.20988],"iteration":620,"passed_time":0.6239938965,"remaining_time":0.3808271928},
{"learn":[66713.79792],"iteration":621,"passed_time":0.6250356476,"remaining_time":0.3798448148},
{"learn":[66665.7839],"iteration":622,"passed_time":0.626074302,"remaining_time":0.3788603721},
{"learn":[66621.95322],"iteration":623,"passed_time":0.6270990237,"remaining_time":0.3778673605},
{"learn":[66553.79075],"iteration":624,"passed_time":0.6281125751,"remaining_time":0.376867545},
{"learn":[66493.81806],"iteration":625,"passed_time":0.629166289,"remaining_time":0.3758916807},
{"learn":[66424.43824],"iteration":626,"passed_time":0.6302810531,"remaining_time":0.3749518865},
{"learn":[66333.20325],"iteration":627,"passed_time":0.631319712,"remaining_time":0.3739664536},
{"learn":[66277.33424],"iteration":628,"passed_time":0.6324467947,"remaining_time":0.3730330061},
{"learn":[66233.39655],"iteration":629,"passed_time":0.6337063018,"remaining_time":0.3721767169},
{"learn":[66198.47897],"iteration":630,"passed_time":0.6347613488,"remaining_time":0.3711995843},
{"learn":[66132.974],"iteration":631,"passed_time":0.635762261,"remaining_time":0.3701906836},
{"learn":[66056.18849],"iteration":632,"passed_time":0.6374286846,"remaining_time":0.3695676576},
{"learn":[65996.64866],"iteration":633,"passed_time":0.6447091505,"remaining_time":0.3721822541},
{"learn":[65943.44904],"iteration":634,"passed_time":0.6465994533,"remaining_time":0.3716674023},
{"learn":[65915.74875],"iteration":635,"passed_time":0.6511232587,"remaining_time":0.37265545},
{"learn":[65838.87969],"iteration":636,"passed_time":0.6533978203,"remaining_time":0.3723444408},
{"learn":[65785.40598],"iteration":637,"passed_time":0.6545418014,"remaining_time":0.371385787},
{"learn":[65703.87607],"iteration":638,"passed_time":0.6556381481,"remaining_time":0.3703996424},
{"learn":[65670.23064],"iteration":639,"passed_time":0.6567250732,"remaining_time":0.3694078537},
{"learn":[65608.3419],"iteration":640,"passed_time":0.6577858236,"remaining_time":0.3684011087},
{"learn":[65539.30066],"iteration":641,"passed_time":0.6588103199,"remaining_time":0.367373979},
{"learn":[65490.83583],"iteration":642,"passed_time":0.6600031705,"remaining_time":0.3664403295},
{"learn":[65453.58761],"iteration":643,"passed_time":0.6610565212,"remaining_time":0.3654287602},
{"learn":[65386.78933],"iteration":644,"passed_time":0.6620454781,"remaining_time":0.3643816197},
{"learn":[65345.35513],"iteration":645,"passed_time":0.663257038,"remaining_time":0.3634566431},
{"learn":[65280.03117],"iteration":646,"passed_time":0.6644466395,"remaining_time":0.3625188002},
{"learn":[65241.26922],"iteration":647,"passed_time":0.6655070033,"remaining_time":0.3615099771},
{"learn":[65184.86057],"iteration":648,"passed_time":0.6666019571,"remaining_time":0.3605197025},
{"learn":[65107.14705],"iteration":649,"passed_time":0.6677640902,"remaining_time":0.3595652793},
{"learn":[65061.03065],"iteration":650,"passed_time":0.6690228004,"remaining_time":0.3586619929},
{"learn":[64997.10727],"iteration":651,"passed_time":0.6701723646,"remaining_time":0.3576993602},
{"learn":[64933.4513],"iteration":652,"passed_time":0.6714143912,"remaining_time":0.356785289},
{"learn":[64906.11736],"iteration":653,"passed_time":0.6724389879,"remaining_time":0.3557551832},
{"learn":[64848.76525],"iteration":654,"passed_time":0.6735487806,"remaining_time":0.3547699684},
{"learn":[64798.31175],"iteration":655,"passed_time":0.6745038023,"remaining_time":0.3537032134},
{"learn":[64733.23353],"iteration":656,"passed_time":0.6754665323,"remaining_time":0.3526408228},
{"learn":[64657.10479],"iteration":657,"passed_time":0.6765304138,"remaining_time":0.3516313093},
{"learn":[64602.4586],"iteration":658,"passed_time":0.6775951584,"remaining_time":0.3506220774},
{"learn":[64571.68062],"iteration":659,"passed_time":0.6785149937,"remaining_time":0.349538027},
{"learn":[64519.23056],"iteration":660,"passed_time":0.67945031,"remaining_time":0.3484624132},
{"learn":[64456.73697],"iteration":661,"passed_time":0.6804052566,"remaining_time":0.3473972458},
{"learn":[64408.09068],"iteration":662,"passed_time":0.6813908689,"remaining_time":0.3463479982},
{"learn":[64371.21532],"iteration":663,"passed_time":0.6823732237,"remaining_time":0.3452972939},
{"learn":[64311.98065],"iteration":664,"passed_time":0.6834560396,"remaining_time":0.3442974034},
{"learn":[64261.77462],"iteration":665,"passed_time":0.684561131,"remaining_time":0.3433084351},
{"learn":[64209.34941],"iteration":666,"passed_time":0.685726281,"remaining_time":0.3423491028},
{"learn":[64140.85327],"iteration":667,"passed_time":0.6868143036,"remaining_time":0.3413508216},
{"learn":[64110.84231],"iteration":668,"passed_time":0.6880600488,"remaining_time":0.3404303081},
{"learn":[64073.78377],"iteration":669,"passed_time":0.6891830468,"remaining_time":0.3394483664},
{"learn":[64049.05881],"iteration":670,"passed_time":0.6903314834,"remaining_time":0.338478477},
{"learn":[63985.64335],"iteration":671,"passed_time":0.6914413914,"remaining_time":0.3374892506},
{"learn":[63899.09456],"iteration":672,"passed_time":0.6924966637,"remaining_time":0.3364731189},
{"learn":[63872.94977],"iteration":673,"passed_time":0.6935281863,"remaining_time":0.3354453839},
{"learn":[63797.1466],"iteration":674,"passed_time":0.6945656026,"remaining_time":0.3344204753},
{"learn":[63756.40793],"iteration":675,"passed_time":0.6956121904,"remaining_time":0.3333999256},
{"learn":[63678.76693],"iteration":676,"passed_time":0.696660872,"remaining_time":0.3323802979},
{"learn":[63634.96939],"iteration":677,"passed_time":0.6977131329,"remaining_time":0.3313622844},
{"learn":[63597.81239],"iteration":678,"passed_time":0.6986824119,"remaining_time":0.3303049399},
{"learn":[63558.13014],"iteration":679,"passed_time":0.6997050644,"remaining_time":0.3292729715},
{"learn":[63526.84844],"iteration":680,"passed_time":0.7007450333,"remaining_time":0.3282491419},
{"learn":[63451.35404],"iteration":681,"passed_time":0.7017497942,"remaining_time":0.3272088483},
{"learn":[63428.74257],"iteration":682,"passed_time":0.7027266313,"remaining_time":0.3261556986},
{"learn":[63322.25082],"iteration":683,"passed_time":0.7038067101,"remaining_time":0.3251504684},
{"learn":[63276.86358],"iteration":684,"passed_time":0.704838333,"remaining_time":0.3241227371},
{"learn":[63236.03279],"iteration":685,"passed_time":0.7058566608,"remaining_time":0.3230889089},
{"learn":[63196.64391],"iteration":686,"passed_time":0.7068786563,"remaining_time":0.3220567968},
{"learn":[63139.07359],"iteration":687,"passed_time":0.7078443776,"remaining_time":0.3209991945},
{"learn":[63099.23023],"iteration":688,"passed_time":0.708843596,"remaining_time":0.3199569787},
{"learn":[63055.43301],"iteration":689,"passed_time":0.7098959413,"remaining_time":0.3189387562},
{"learn":[63020.56538],"iteration":690,"passed_time":0.7109326058,"remaining_time":0.3179134228},
{"learn":[62997.48944],"iteration":691,"passed_time":0.7118674112,"remaining_time":0.3168427206},
{"learn":[62943.29238],"iteration":692,"passed_time":0.7127797846,"remaining_time":0.3157624731},
{"learn":[62849.56593],"iteration":693,"passed_time":0.713740665,"remaining_time":0.3147040973},
{"learn":[62804.31266],"iteration":694,"passed_time":0.714692324,"remaining_time":0.3136419551},
{"learn":[62728.77982],"iteration":695,"passed_time":0.7156255806,"remaining_time":0.3125720927},
{"learn":[62656.78635],"iteration":696,"passed_time":0.7166525525,"remaining_time":0.3115433622},
{"learn":[62642.78194],"iteration":697,"passed_time":0.7175736164,"remaining_time":0.310468814},
{"learn":[62610.18497],"iteration":698,"passed_time":0.7185074544,"remaining_time":0.3094002057},
{"learn":[62576.58984],"iteration":699,"passed_time":0.7194952615,"remaining_time":0.3083551121},
{"learn":[62534.17144],"iteration":700,"passed_time":0.7206078904,"remaining_time":0.3073634226},
{"learn":[62496.03677],"iteration":701,"passed_time":0.7217281443,"remaining_time":0.3063746254},
{"learn":[62401.4875],"iteration":702,"passed_time":0.722964822,"remaining_time":0.3054346403},
{"learn":[62324.1357],"iteration":703,"passed_time":0.7240037214,"remaining_time":0.3044106556},
{"learn":[62267.29416],"iteration":704,"passed_time":0.7249481888,"remaining_time":0.3033471145},
{"learn":[62230.55826],"iteration":705,"passed_time":0.7260322523,"remaining_time":0.3023420427},
{"learn":[62197.19438],"iteration":706,"passed_time":0.726973808,"remaining_time":0.3012776885},
{"learn":[62119.08069],"iteration":707,"passed_time":0.7279390538,"remaining_time":0.3002234516},
{"learn":[62064.33695],"iteration":708,"passed_time":0.7289169375,"remaining_time":0.2991746528},
{"learn":[62038.54488],"iteration":709,"passed_time":0.7298476583,"remaining_time":0.29810679},
{"learn":[61996.92295],"iteration":710,"passed_time":0.730745709,"remaining_time":0.2970260336},
{"learn":[61927.44472],"iteration":711,"passed_time":0.731677402,"remaining_time":0.2959593986},
{"learn":[61879.00048],"iteration":712,"passed_time":0.7326649741,"remaining_time":0.2949156347},
{"learn":[61846.09313],"iteration":713,"passed_time":0.7336044796,"remaining_time":0.2938527747},
{"learn":[61830.2392],"iteration":714,"passed_time":0.7345997639,"remaining_time":0.2928124933},
{"learn":[61799.92793],"iteration":715,"passed_time":0.7355973256,"remaining_time":0.2917732409},
{"learn":[61729.54326],"iteration":716,"passed_time":0.7366034327,"remaining_time":0.2907374776},
{"learn":[61700.76685],"iteration":717,"passed_time":0.737572652,"remaining_time":0.289687309},
{"learn":[61658.79122],"iteration":718,"passed_time":0.7384716,"remaining_time":0.2886099021},
{"learn":[61623.73451],"iteration":719,"passed_time":0.7395207334,"remaining_time":0.2875913963},
{"learn":[61564.12152],"iteration":720,"passed_time":0.7405110379,"remaining_time":0.286550041},
{"learn":[61521.20661],"iteration":721,"passed_time":0.7416361489,"remaining_time":0.2855607332},
{"learn":[61459.80986],"iteration":722,"passed_time":0.7427057191,"remaining_time":0.2845497707},
{"learn":[61429.90396],"iteration":723,"passed_time":0.7436189194,"remaining_time":0.2834790356},
{"learn":[61407.10785],"iteration":724,"passed_time":0.7445127854,"remaining_time":0.2824014014},
{"learn":[61388.50361],"iteration":725,"passed_time":0.7454163988,"remaining_time":0.2813279522},
{"learn":[61341.34225],"iteration":726,"passed_time":0.7463824659,"remaining_time":0.2802784226},
{"learn":[61308.34621],"iteration":727,"passed_time":0.7473921985,"remaining_time":0.2792454368},
{"learn":[61265.68116],"iteration":728,"passed_time":0.7483812384,"remaining_time":0.2782048225},
{"learn":[61227.46435],"iteration":729,"passed_time":0.7493804518,"remaining_time":0.2771681123},
{"learn":[61171.91665],"iteration":730,"passed_time":0.7503835491,"remaining_time":0.2761329339},
{"learn":[61123.7393],"iteration":731,"passed_time":0.7514957576,"remaining_time":0.275137791},
{"learn":[61091.92403],"iteration":732,"passed_time":0.7525440986,"remaining_time":0.2741190646},
{"learn":[61040.12211],"iteration":733,"passed_time":0.7536751571,"remaining_time":0.273130234},
{"learn":[61002.88974],"iteration":734,"passed_time":0.7547417135,"remaining_time":0.2721177607},
{"learn":[60968.03747],"iteration":735,"passed_time":0.7556985095,"remaining_time":0.2710657697},
{"learn":[60946.39467],"iteration":736,"passed_time":0.7566777367,"remaining_time":0.2700220417},
{"learn":[60890.07956],"iteration":737,"passed_time":0.7576098103,"remaining_time":0.2689617484},
{"learn":[60824.09691],"iteration":738,"passed_time":0.758533079,"remaining_time":0.2678986923},
{"learn":[60787.8171],"iteration":739,"passed_time":0.759485189,"remaining_time":0.2668461475},
{"learn":[60731.07738],"iteration":740,"passed_time":0.7603889878,"remaining_time":0.2657769877},
{"learn":[60657.6895],"iteration":741,"passed_time":0.7613253667,"remaining_time":0.2647196019},
{"learn":[60624.04915],"iteration":742,"passed_time":0.7622497729,"remaining_time":0.2636584006},
{"learn":[60577.62876],"iteration":743,"passed_time":0.7631698092,"remaining_time":0.2625960634},
{"learn":[60551.59511],"iteration":744,"passed_time":0.7642274021,"remaining_time":0.2615811913},
{"learn":[60511.32385],"iteration":745,"passed_time":0.7651726761,"remaining_time":0.2605279621},
{"learn":[60474.18714],"iteration":746,"passed_time":0.7661304744,"remaining_time":0.2594792638},
{"learn":[60431.13082],"iteration":747,"passed_time":0.7672499692,"remaining_time":0.2584852837},
{"learn":[60349.90848],"iteration":748,"passed_time":0.7683845338,"remaining_time":0.2574960187},
{"learn":[60318.95572],"iteration":749,"passed_time":0.7694285101,"remaining_time":0.25647617},
{"learn":[60244.42936],"iteration":750,"passed_time":0.7704289814,"remaining_time":0.2554418327},
{"learn":[60200.52118],"iteration":751,"passed_time":0.7714856268,"remaining_time":0.254426111},
{"learn":[60149.6892],"iteration":752,"passed_time":0.7724741155,"remaining_time":0.2533879237},
{"learn":[60121.5413],"iteration":753,"passed_time":0.7734340387,"remaining_time":0.2523405484},
{"learn":[60097.45314],"iteration":754,"passed_time":0.7745148851,"remaining_time":0.2513326448},
{"learn":[60081.34306],"iteration":755,"passed_time":0.7755275138,"remaining_time":0.2503025309},
{"learn":[60034.98079],"iteration":756,"passed_time":0.7765071875,"remaining_time":0.2492618845},
{"learn":[59988.81883],"iteration":757,"passed_time":0.7775327266,"remaining_time":0.248236042},
{"learn":[59944.95518],"iteration":758,"passed_time":0.7785987682,"remaining_time":0.2472230608},
{"learn":[59928.07482],"iteration":759,"passed_time":0.7796270336,"remaining_time":0.2461980106},
{"learn":[59901.634],"iteration":760,"passed_time":0.7807109117,"remaining_time":0.2451904177},
{"learn":[59841.77359],"iteration":761,"passed_time":0.781977059,"remaining_time":0.2442395539},
{"learn":[59806.58673],"iteration":762,"passed_time":0.7830908264,"remaining_time":0.2432405319},
{"learn":[59757.59394],"iteration":763,"passed_time":0.7842755509,"remaining_time":0.2422631283},
{"learn":[59729.64067],"iteration":764,"passed_time":0.7853131375,"remaining_time":0.2412399834},
{"learn":[59700.28489],"iteration":765,"passed_time":0.7863714589,"remaining_time":0.240223135},
{"learn":[59657.67575],"iteration":766,"passed_time":0.7874581266,"remaining_time":0.2392147894},
{"learn":[59584.60746],"iteration":767,"passed_time":0.7884972921,"remaining_time":0.2381918903},
{"learn":[59518.90336],"iteration":768,"passed_time":0.7895564678,"remaining_time":0.2371749598},
{"learn":[59488.17329],"iteration":769,"passed_time":0.7906065804,"remaining_time":0.2361552123},
{"learn":[59418.53198],"iteration":770,"passed_time":0.7916401105,"remaining_time":0.2351304608},
{"learn":[59379.62038],"iteration":771,"passed_time":0.7926631107,"remaining_time":0.2341025767},
{"learn":[59349.09708],"iteration":772,"passed_time":0.7937679148,"remaining_time":0.2330987279},
{"learn":[59319.70529],"iteration":773,"passed_time":0.7947587441,"remaining_time":0.2320613387},
{"learn":[59251.71963],"iteration":774,"passed_time":0.7958833108,"remaining_time":0.2310628967},
{"learn":[59186.4163],"iteration":775,"passed_time":0.7968866386,"remaining_time":0.2300291328},
{"learn":[59158.93113],"iteration":776,"passed_time":0.7978622524,"remaining_time":0.2289874933},
{"learn":[59121.27548],"iteration":777,"passed_time":0.7989188828,"remaining_time":0.2279691414},
{"learn":[59078.33964],"iteration":778,"passed_time":0.7999563041,"remaining_time":0.2269452416},
{"learn":[59049.32601],"iteration":779,"passed_time":0.800996647,"remaining_time":0.2259221312},
{"learn":[59017.01944],"iteration":780,"passed_time":0.8019887843,"remaining_time":0.2248854594},
{"learn":[58978.83742],"iteration":781,"passed_time":0.8029922622,"remaining_time":0.2238520629},
{"learn":[58955.27932],"iteration":782,"passed_time":0.8039553881,"remaining_time":0.2228075597},
{"learn":[58918.60914],"iteration":783,"passed_time":0.805019372,"remaining_time":0.2217910515},
{"learn":[58886.58602],"iteration":784,"passed_time":0.8059624547,"remaining_time":0.2207413092},
{"learn":[58827.76082],"iteration":785,"passed_time":0.8071107855,"remaining_time":0.2197477202},
{"learn":[58806.12801],"iteration":786,"passed_time":0.8081698214,"remaining_time":0.2187295705},
{"learn":[58777.16489],"iteration":787,"passed_time":0.8092551782,"remaining_time":0.2177183982},
{"learn":[58721.22271],"iteration":788,"passed_time":0.8102487404,"remaining_time":0.2166824895},
{"learn":[58690.23554],"iteration":789,"passed_time":0.8113087786,"remaining_time":0.2156643589},
{"learn":[58660.60117],"iteration":790,"passed_time":0.8123225003,"remaining_time":0.2146338844},
{"learn":[58624.73444],"iteration":791,"passed_time":0.8135488139,"remaining_time":0.2136592845},
{"learn":[58565.46076],"iteration":792,"passed_time":0.8145907658,"remaining_time":0.212635925},
{"learn":[58553.18164],"iteration":793,"passed_time":0.8157203288,"remaining_time":0.211635249},
{"learn":[58521.87015],"iteration":794,"passed_time":0.8166585922,"remaining_time":0.21058492},
{"learn":[58483.07173],"iteration":795,"passed_time":0.8176815398,"remaining_time":0.2095565755},
{"learn":[58443.53797],"iteration":796,"passed_time":0.818625441,"remaining_time":0.2085081111},
{"learn":[58407.89946],"iteration":797,"passed_time":0.8196812798,"remaining_time":0.2074882438},
{"learn":[58387.11122],"iteration":798,"passed_time":0.8207011757,"remaining_time":0.2064592445},
{"learn":[58357.54688],"iteration":799,"passed_time":0.8217537969,"remaining_time":0.2054384492},
{"learn":[58318.24578],"iteration":800,"passed_time":0.8227474528,"remaining_time":0.2044029252},
{"learn":[58292.43592],"iteration":801,"passed_time":0.8238141661,"remaining_time":0.2033855423},
{"learn":[58264.69163],"iteration":802,"passed_time":0.8247953833,"remaining_time":0.2023470617},
{"learn":[58209.09336],"iteration":803,"passed_time":0.8257357764,"remaining_time":0.2012987714},
{"learn":[58179.90838],"iteration":804,"passed_time":0.8267326546,"remaining_time":0.2002644319},
{"learn":[58106.21153],"iteration":805,"passed_time":0.8277691133,"remaining_time":0.1992397121},
{"learn":[58062.26239],"iteration":806,"passed_time":0.8288898164,"remaining_time":0.198235111},
{"learn":[58036.36818],"iteration":807,"passed_time":0.8298687782,"remaining_time":0.1971965413},
{"learn":[58018.12537],"iteration":808,"passed_time":0.8308241412,"remaining_time":0.1961525475},
{"learn":[57973.31918],"iteration":809,"passed_time":0.8318261003,"remaining_time":0.1951197025},
{"learn":[57945.92039],"iteration":810,"passed_time":0.8328471689,"remaining_time":0.1940913871},
{"learn":[57920.3601],"iteration":811,"passed_time":0.8338811673,"remaining_time":0.1930660831},
{"learn":[57885.98176],"iteration":812,"passed_time":0.8348148349,"remaining_time":0.1920176803},
{"learn":[57871.4242],"iteration":813,"passed_time":0.835768759,"remaining_time":0.1909741882},
{"learn":[57822.62605],"iteration":814,"passed_time":0.836763006,"remaining_time":0.1899400688},
{"learn":[57753.05824],"iteration":815,"passed_time":0.8377580547,"remaining_time":0.188906228},
{"learn":[57696.25757],"iteration":816,"passed_time":0.83872116,"remaining_time":0.1878653272},
{"learn":[57656.96149],"iteration":817,"passed_time":0.8396243675,"remaining_time":0.1868112896},
{"learn":[57619.08249],"iteration":818,"passed_time":0.8405693411,"remaining_time":0.1857668507},
{"learn":[57568.79771],"iteration":819,"passed_time":0.8415521718,"remaining_time":0.1847309645},
{"learn":[57548.11078],"iteration":820,"passed_time":0.8425424496,"remaining_time":0.1836968313},
{"learn":[57510.76819],"iteration":821,"passed_time":0.8435491106,"remaining_time":0.1826663524},
{"learn":[57476.30364],"iteration":822,"passed_time":0.8445180588,"remaining_time":0.1816278207},
{"learn":[57453.23127],"iteration":823,"passed_time":0.845555355,"remaining_time":0.1806040564},
{"learn":[57429.70119],"iteration":824,"passed_time":0.8466164554,"remaining_time":0.1795853087},
{"learn":[57369.89515],"iteration":825,"passed_time":0.8477571695,"remaining_time":0.1785832294},
{"learn":[57326.63103],"iteration":826,"passed_time":0.8488529299,"remaining_time":0.177571411},
{"learn":[57272.30568],"iteration":827,"passed_time":0.8500003238,"remaining_time":0.1765701156},
{"learn":[57234.36995],"iteration":828,"passed_time":0.8510922254,"remaining_time":0.1755570212},
{"learn":[57197.10312],"iteration":829,"passed_time":0.8523910479,"remaining_time":0.1745861182},
{"learn":[57164.60541],"iteration":830,"passed_time":0.8535782586,"remaining_time":0.1735917277},
{"learn":[57136.11384],"iteration":831,"passed_time":0.854658784,"remaining_time":0.1725753314},
{"learn":[57081.96087],"iteration":832,"passed_time":0.8557489919,"remaining_time":0.1715607223},
{"learn":[57052.57839],"iteration":833,"passed_time":0.8568379364,"remaining_time":0.1705456804},
{"learn":[57017.05673],"iteration":834,"passed_time":0.8577152644,"remaining_time":0.1694886451},
{"learn":[56959.71485],"iteration":835,"passed_time":0.8586878715,"remaining_time":0.1684507308},
{"learn":[56931.25764],"iteration":836,"passed_time":0.8596442413,"remaining_time":0.1674098104},
{"learn":[56902.60152],"iteration":837,"passed_time":0.8605107745,"remaining_time":0.1663517249},
{"learn":[56851.8326],"iteration":838,"passed_time":0.8614838327,"remaining_time":0.1653145376},
{"learn":[56810.47203],"iteration":839,"passed_time":0.8624614516,"remaining_time":0.1642783717},
{"learn":[56773.96836],"iteration":840,"passed_time":0.863381999,"remaining_time":0.1632315551},
{"learn":[56729.73909],"iteration":841,"passed_time":0.8642657486,"remaining_time":0.1621781334},
{"learn":[56682.1074],"iteration":842,"passed_time":0.8653697862,"remaining_time":0.1611661405},
{"learn":[56647.59156],"iteration":843,"passed_time":0.866311056,"remaining_time":0.1601238445},
{"learn":[56626.30081],"iteration":844,"passed_time":0.8673935531,"remaining_time":0.1591076932},
{"learn":[56591.25761],"iteration":845,"passed_time":0.8683516001,"remaining_time":0.158068731},
{"learn":[56558.1733],"iteration":846,"passed_time":0.8693198639,"remaining_time":0.1570318054},
{"learn":[56533.26887],"iteration":847,"passed_time":0.8702769983,"remaining_time":0.1559930469},
{"learn":[56506.57268],"iteration":848,"passed_time":0.8712437821,"remaining_time":0.1549561968},
{"learn":[56484.07282],"iteration":849,"passed_time":0.872091963,"remaining_time":0.1538985817},
{"learn":[56461.10541],"iteration":850,"passed_time":0.8730803367,"remaining_time":0.1528660049},
{"learn":[56433.94945],"iteration":851,"passed_time":0.8740038008,"remaining_time":0.1518222565},
{"learn":[56401.47739],"iteration":852,"passed_time":0.8750439731,"remaining_time":0.1507989028},
{"learn":[56362.99218],"iteration":853,"passed_time":0.8759573139,"remaining_time":0.1497538265},
{"learn":[56327.88166],"iteration":854,"passed_time":0.8769101706,"remaining_time":0.1487157599},
{"learn":[56300.31158],"iteration":855,"passed_time":0.8778678635,"remaining_time":0.147678706},
{"learn":[56265.0061],"iteration":856,"passed_time":0.8788082515,"remaining_time":0.1466389498},
{"learn":[56229.44583],"iteration":857,"passed_time":0.8798269146,"remaining_time":0.1456123798},
{"learn":[56184.09208],"iteration":858,"passed_time":0.8808775916,"remaining_time":0.1445910831},
{"learn":[56141.55176],"iteration":859,"passed_time":0.8818438009,"remaining_time":0.1435559676},
{"learn":[56109.19892],"iteration":860,"passed_time":0.8828774083,"remaining_time":0.1425318929},
{"learn":[56081.30863],"iteration":861,"passed_time":0.8839509909,"remaining_time":0.1415141958},
{"learn":[56049.38318],"iteration":862,"passed_time":0.8849751967,"remaining_time":0.1404885306},
{"learn":[56037.5043],"iteration":863,"passed_time":0.8859268359,"remaining_time":0.1394514464},
{"learn":[56002.68818],"iteration":864,"passed_time":0.8867898209,"remaining_time":0.1384007235},
{"learn":[55975.46119],"iteration":865,"passed_time":0.8876788859,"remaining_time":0.1373544696},
{"learn":[55923.1118],"iteration":866,"passed_time":0.8886058378,"remaining_time":0.1363143903},
{"learn":[55890.01554],"iteration":867,"passed_time":0.8894822837,"remaining_time":0.1352668911},
{"learn":[55862.56579],"iteration":868,"passed_time":0.8905382028,"remaining_time":0.1342468407},
{"learn":[55840.15495],"iteration":869,"passed_time":0.891481843,"remaining_time":0.1332099306},
{"learn":[55793.81722],"iteration":870,"passed_time":0.8924739252,"remaining_time":0.1321804091},
{"learn":[55763.33284],"iteration":871,"passed_time":0.8934270473,"remaining_time":0.1311452546},
{"learn":[55725.08563],"iteration":872,"passed_time":0.8943288315,"remaining_time":0.1301028197},
{"learn":[55694.60323],"iteration":873,"passed_time":0.8952235767,"remaining_time":0.1290596918},
{"learn":[55654.08377],"iteration":874,"passed_time":0.8961373385,"remaining_time":0.1280196198},
{"learn":[55622.6926],"iteration":875,"passed_time":0.8971647398,"remaining_time":0.1269959221},
{"learn":[55586.18168],"iteration":876,"passed_time":0.8980754947,"remaining_time":0.1259558562},
{"learn":[55552.80202],"iteration":877,"passed_time":0.8990376729,"remaining_time":0.1249232302},
{"learn":[55526.80141],"iteration":878,"passed_time":0.9000184588,"remaining_time":0.123893326},
{"learn":[55495.76762],"iteration":879,"passed_time":0.9009955663,"remaining_time":0.1228630318},
{"learn":[55474.92411],"iteration":880,"passed_time":0.9018773646,"remaining_time":0.1218199845},
{"learn":[55440.59545],"iteration":881,"passed_time":0.9027441684,"remaining_time":0.1207752969},
{"learn":[55417.60909],"iteration":882,"passed_time":0.9036811433,"remaining_time":0.11974031},
{"learn":[55384.25325],"iteration":883,"passed_time":0.9046864156,"remaining_time":0.118714507},
{"learn":[55359.85309],"iteration":884,"passed_time":0.9056447098,"remaining_time":0.1176826459},
{"learn":[55348.89099],"iteration":885,"passed_time":0.9066234009,"remaining_time":0.1166535753},
{"learn":[55317.71823],"iteration":886,"passed_time":0.9076213063,"remaining_time":0.1156270661},
{"learn":[55271.14091],"iteration":887,"passed_time":0.908605049,"remaining_time":0.114598835},
{"learn":[55220.17203],"iteration":888,"passed_time":0.9095308385,"remaining_time":0.113563468},
{"learn":[55188.49457],"iteration":889,"passed_time":0.9104954876,"remaining_time":0.1125331502},
{"learn":[55167.90309],"iteration":890,"passed_time":0.9115308939,"remaining_time":0.1115116357},
{"learn":[55132.81249],"iteration":891,"passed_time":0.9125598607,"remaining_time":0.1104893105},
{"learn":[55091.92437],"iteration":892,"passed_time":0.9135367733,"remaining_time":0.1094607332},
{"learn":[55059.73479],"iteration":893,"passed_time":0.9144499537,"remaining_time":0.1084247149},
{"learn":[55023.88036],"iteration":894,"passed_time":0.9153124877,"remaining_time":0.1073830293},
{"learn":[54999.69696],"iteration":895,"passed_time":0.916205151,"remaining_time":0.1063452407},
{"learn":[54965.23745],"iteration":896,"passed_time":0.9171276223,"remaining_time":0.1053111985},
{"learn":[54941.35169],"iteration":897,"passed_time":0.9180319323,"remaining_time":0.104275342},
{"learn":[54923.20206],"iteration":898,"passed_time":0.9189047399,"remaining_time":0.1032362389},
{"learn":[54900.54258],"iteration":899,"passed_time":0.9198385679,"remaining_time":0.1022042853},
{"learn":[54867.12823],"iteration":900,"passed_time":0.9207730774,"remaining_time":0.1011726245},
{"learn":[54823.53087],"iteration":901,"passed_time":0.9216643174,"remaining_time":0.1001364779},
{"learn":[54792.15008],"iteration":902,"passed_time":0.9226166529,"remaining_time":0.09910721521},
{"learn":[54767.43612],"iteration":903,"passed_time":0.9235682267,"remaining_time":0.09807804177},
{"learn":[54736.77672],"iteration":904,"passed_time":0.9244944371,"remaining_time":0.09704637737},
{"learn":[54717.98828],"iteration":905,"passed_time":0.925376947,"remaining_time":0.09601041172},
{"learn":[54675.20653],"iteration":906,"passed_time":0.9262392304,"remaining_time":0.0949727105},
{"learn":[54633.2175],"iteration":907,"passed_time":0.9271345898,"remaining_time":0.09393874699},
{"learn":[54601.6491],"iteration":908,"passed_time":0.9280513485,"remaining_time":0.09290723071},
{"learn":[54565.41317],"iteration":909,"passed_time":0.9288969135,"remaining_time":0.09186892551},
{"learn":[54532.77866],"iteration":910,"passed_time":0.9298420179,"remaining_time":0.09084076794},
{"learn":[54494.46457],"iteration":911,"passed_time":0.9307384799,"remaining_time":0.08980809894},
{"learn":[54460.95673],"iteration":912,"passed_time":0.9316855182,"remaining_time":0.08878054774},
{"learn":[54423.04527],"iteration":913,"passed_time":0.9325259914,"remaining_time":0.0877431458},
{"learn":[54395.5093],"iteration":914,"passed_time":0.9334296901,"remaining_time":0.08671204771},
{"learn":[54369.82913],"iteration":915,"passed_time":0.9343272847,"remaining_time":0.08568066803},
{"learn":[54354.5978],"iteration":916,"passed_time":0.9352273049,"remaining_time":0.08464979968},
{"learn":[54318.12093],"iteration":917,"passed_time":0.9362355986,"remaining_time":0.08362888789},
{"learn":[54294.14717],"iteration":918,"passed_time":0.9371340254,"remaining_time":0.08259831997},
{"learn":[54266.00064],"iteration":919,"passed_time":0.9380641147,"remaining_time":0.08157079258},
{"learn":[54244.51251],"iteration":920,"passed_time":0.9389635034,"remaining_time":0.0805408434},
{"learn":[54215.47447],"iteration":921,"passed_time":0.9398474066,"remaining_time":0.07950986737},
{"learn":[54187.78976],"iteration":922,"passed_time":0.9407425856,"remaining_time":0.07848015069},
{"learn":[54153.1654],"iteration":923,"passed_time":0.9416832493,"remaining_time":0.07745446639},
{"learn":[54123.47918],"iteration":924,"passed_time":0.9426349831,"remaining_time":0.0764298635},
{"learn":[54105.54098],"iteration":925,"passed_time":0.9436847578,"remaining_time":0.07541325278},
{"learn":[54080.71563],"iteration":926,"passed_time":0.9446379155,"remaining_time":0.07438896206},
{"learn":[54061.37187],"iteration":927,"passed_time":0.9455333852,"remaining_time":0.07336034885},
{"learn":[54019.43654],"iteration":928,"passed_time":0.9464075158,"remaining_time":0.07233039141},
{"learn":[53980.58108],"iteration":929,"passed_time":0.9472856657,"remaining_time":0.07130107161},
{"learn":[53953.79554],"iteration":930,"passed_time":0.9482130588,"remaining_time":0.07027572617},
{"learn":[53937.37633],"iteration":931,"passed_time":0.9490956437,"remaining_time":0.06924732164},
{"learn":[53907.79406],"iteration":932,"passed_time":0.9500680606,"remaining_time":0.06822568067},
{"learn":[53870.01011],"iteration":933,"passed_time":0.9509593808,"remaining_time":0.06719841449},
{"learn":[53854.46137],"iteration":934,"passed_time":0.9518554519,"remaining_time":0.06617176938},
{"learn":[53837.83743],"iteration":935,"passed_time":0.9527574063,"remaining_time":0.06514580556},
{"learn":[53817.60769],"iteration":936,"passed_time":0.9536436748,"remaining_time":0.06411905178},
{"learn":[53768.08524],"iteration":937,"passed_time":0.9545530465,"remaining_time":0.06309412461},
{"learn":[53751.18868],"iteration":938,"passed_time":0.9555463315,"remaining_time":0.06207489481},
{"learn":[53734.14175],"iteration":939,"passed_time":0.9564533578,"remaining_time":0.06105021433},
{"learn":[53715.58611],"iteration":940,"passed_time":0.9573710687,"remaining_time":0.06002645383},
{"learn":[53694.68474],"iteration":941,"passed_time":0.9582670295,"remaining_time":0.05900157931},
{"learn":[53675.00964],"iteration":942,"passed_time":0.9591534384,"remaining_time":0.05797640084},
{"learn":[53652.00395],"iteration":943,"passed_time":0.9600241311,"remaining_time":0.05695058405},
{"learn":[53618.31758],"iteration":944,"passed_time":0.9609570971,"remaining_time":0.05592871994},
{"learn":[53584.9937],"iteration":945,"passed_time":0.9618702976,"remaining_time":0.05490591551},
{"learn":[53542.42797],"iteration":946,"passed_time":0.9627685437,"remaining_time":0.05388250561},
{"learn":[53517.62617],"iteration":947,"passed_time":0.9636789678,"remaining_time":0.05286002777},
{"learn":[53496.99392],"iteration":948,"passed_time":0.9649109012,"remaining_time":0.05185506424},
{"learn":[53485.49875],"iteration":949,"passed_time":0.9660005977,"remaining_time":0.05084213672},
{"learn":[53450.41664],"iteration":950,"passed_time":0.9669938294,"remaining_time":0.04982407743},
{"learn":[53416.86137],"iteration":951,"passed_time":0.9679066624,"remaining_time":0.04880201659},
{"learn":[53396.57176],"iteration":952,"passed_time":0.9688839303,"remaining_time":0.04778336278},
{"learn":[53372.78509],"iteration":953,"passed_time":0.9698641149,"remaining_time":0.04676493636},
{"learn":[53351.66194],"iteration":954,"passed_time":0.9709230873,"remaining_time":0.04575030254},
{"learn":[53325.23042],"iteration":955,"passed_time":0.9718893229,"remaining_time":0.04473130775},
{"learn":[53301.25828],"iteration":956,"passed_time":0.9728787335,"remaining_time":0.04371346451},
{"learn":[53277.4024],"iteration":957,"passed_time":0.9738376541,"remaining_time":0.04269434392},
{"learn":[53263.97706],"iteration":958,"passed_time":0.9748724443,"remaining_time":0.04167859251},
{"learn":[53237.74362],"iteration":959,"passed_time":0.976066782,"remaining_time":0.04066944925},
{"learn":[53213.90688],"iteration":960,"passed_time":0.9770665416,"remaining_time":0.03965202406},
{"learn":[53182.43296],"iteration":961,"passed_time":0.9781331249,"remaining_time":0.0386372752},
{"learn":[53164.73435],"iteration":962,"passed_time":0.9791163064,"remaining_time":0.03761921426},
{"learn":[53141.4617],"iteration":963,"passed_time":0.9800998853,"remaining_time":0.03660124053},
{"learn":[53122.54072],"iteration":964,"passed_time":0.9812489964,"remaining_time":0.03558934184},
{"learn":[53096.68037],"iteration":965,"passed_time":0.9822037224,"remaining_time":0.03457031735},
{"learn":[53076.38322],"iteration":966,"passed_time":0.9831595459,"remaining_time":0.0335514633},
{"learn":[53047.433],"iteration":967,"passed_time":0.9841219702,"remaining_time":0.03253295769},
{"learn":[53026.26243],"iteration":968,"passed_time":0.9850175747,"remaining_time":0.03151243015},
{"learn":[53005.99246],"iteration":969,"passed_time":0.9859771919,"remaining_time":0.03049413996},
{"learn":[52986.14149],"iteration":970,"passed_time":0.9869426176,"remaining_time":0.02947614409},
{"learn":[52955.6485],"iteration":971,"passed_time":0.9879552818,"remaining_time":0.02845961717},
{"learn":[52899.6218],"iteration":972,"passed_time":0.9889264156,"remaining_time":0.02744194576},
{"learn":[52866.53141],"iteration":973,"passed_time":0.9898711038,"remaining_time":0.02642366396},
{"learn":[52840.75944],"iteration":974,"passed_time":0.9908862986,"remaining_time":0.02540734099},
{"learn":[52789.55636],"iteration":975,"passed_time":0.9918621132,"remaining_time":0.02439005196},
{"learn":[52756.53699],"iteration":976,"passed_time":0.9928555553,"remaining_time":0.02337326282},
{"learn":[52731.67778],"iteration":977,"passed_time":0.993763704,"remaining_time":0.02235460275},
{"learn":[52720.82914],"iteration":978,"passed_time":0.9946812249,"remaining_time":0.02133636948},
{"learn":[52676.95668],"iteration":979,"passed_time":0.9956530152,"remaining_time":0.02031944929},
{"learn":[52644.78152],"iteration":980,"passed_time":0.9965969163,"remaining_time":0.01930208095},
{"learn":[52625.66698],"iteration":981,"passed_time":0.9975520939,"remaining_time":0.01828506893},
{"learn":[52590.63208],"iteration":982,"passed_time":0.9985389182,"remaining_time":0.01726873002},
{"learn":[52561.31266],"iteration":983,"passed_time":0.9995335711,"remaining_time":0.01625257839},
{"learn":[52533.034],"iteration":984,"passed_time":1.000517725,"remaining_time":0.01523631053},
{"learn":[52521.08243],"iteration":985,"passed_time":1.001490317,"remaining_time":0.01421994365},
{"learn":[52494.54353],"iteration":986,"passed_time":1.002481166,"remaining_time":0.01320390594},
{"learn":[52472.1542],"iteration":987,"passed_time":1.00341562,"remaining_time":0.01218723426},
{"learn":[52452.50664],"iteration":988,"passed_time":1.004401142,"remaining_time":0.01117129683},
{"learn":[52435.17663],"iteration":989,"passed_time":1.005356329,"remaining_time":0.01015511444},
{"learn":[52401.4842],"iteration":990,"passed_time":1.006340478,"remaining_time":0.009139318166},
{"learn":[52388.67699],"iteration":991,"passed_time":1.007367871,"remaining_time":0.008123934447},
{"learn":[52365.06369],"iteration":992,"passed_time":1.008515451,"remaining_time":0.007109373772},
{"learn":[52347.02759],"iteration":993,"passed_time":1.009417365,"remaining_time":0.006093062567},
{"learn":[52321.52719],"iteration":994,"passed_time":1.010400056,"remaining_time":0.005077387216},
{"learn":[52298.64791],"iteration":995,"passed_time":1.011379218,"remaining_time":0.004061763928},
{"learn":[52281.01668],"iteration":996,"passed_time":1.012350041,"remaining_time":0.00304618869},
{"learn":[52243.78838],"iteration":997,"passed_time":1.013276192,"remaining_time":0.002030613611},
{"learn":[52220.90324],"iteration":998,"passed_time":1.014256206,"remaining_time":0.001015271477},
{"learn":[52198.98739],"iteration":999,"passed_time":1.015246243,"remaining_time":0}
]}